<?xml version="1.0"?>
<!DOCTYPE wetgeving SYSTEM "http://wetten.overheid.nl/dtd/bwb-plus-meta-1_61w.dtd">
<wetgeving bwb-id="BWBR0012858" dtdversie="2.0" id="77389" soort="wet" xml:lang="nl">
    
    <intitule>Wet van 27 september 2001 tot wijziging van de begroting van
    de uitgaven en de ontvangsten van het Fonds economische
    structuurversterking voor het jaar 2001 (wijziging samenhangende met
    de Voorjaarsnota)</intitule>
    
    <wet-besluit>
        <aanhef>
    <wij>Wij Beatrix, bij de gratie Gods, Koningin der Nederlanden,
        Prinses van Oranje-Nassau, enz. enz. enz.</wij>
    <considerans>
        <considerans.al>Allen, die deze zullen zien of horen lezen,
            saluut! doen te weten:</considerans.al>
        <considerans.al>Alzo Wij in overweging genomen hebben, dat de
            noodzaak is gebleken van een wijziging van de begroting van
            de uitgaven en de ontvangsten van het Rijk, vastgesteld bij
            de wet van 12 februari 2001, Stb. 138;</considerans.al>
    </considerans>
    <afkondiging>
        <al>Zo is het, dat Wij met gemeen overleg der Staten-Generaal,
            hebben goedgevonden en verstaan, gelijk Wij goedvinden en
            verstaan bij deze:</al>
    </afkondiging>
</aanhef>
        <wettekst>
            <artikel status="goed">
    <kop>
        <label>Artikel</label>
        <nr>1</nr>
    </kop>
    <al>De begroting van de uitgaven van het Fonds economische
        structuurversterking voor het jaar 2001 wordt gewijzigd, zoals
        blijkt uit kolom 2 van de bij deze wet behorende
        begrotingsstaat, onderdeel uitgaven.</al>
</artikel>
            <artikel status="goed">
    <kop>
        <label>Artikel</label>
        <nr>2</nr>
    </kop>
    <al>De begroting van de ontvangsten van het Fonds economische
        structuurversterking voor het jaar 2001 wordt gewijzigd, zoals
        blijkt uit kolom 2 van de bij deze wet behorende
        begrotingsstaat, onderdeel ontvangsten.</al>
</artikel>
            <artikel status="goed">
    <kop>
        <label>Artikel</label>
        <nr>3</nr>
    </kop>
    <al>In afwijking van het bepaalde in <extref status="actief" doc="1.0:v:BWBR0007788&amp;artikel=2" compleet="nee">artikel 2, eerste lid, aanhef en
            onder b, juncto tweede lid, aanhef en onder c, van de Wet
            Fonds economische structuurversterking</extref>,
        laatstelijk gewijzigd bij de wet van 30 november 2000 (Stb.
        2000, 552), worden de opbrengsten van de veiling van
        UMTS-frequenties in 2000 met ingang van 1 januari 2001 ten
        gunste van het Fes gebracht via een annu&#xEF;teit met een looptijd
        van 15 jaar.</al>
</artikel>
            <artikel status="goed">
    <kop>
        <label>Artikel</label>
        <nr>4</nr>
    </kop>
    <al>Deze wet treedt in werking met ingang van 1 juni van het
        onderhavige begrotingsjaar. Indien het Staatsblad waarin deze
        wet wordt geplaatst, wordt uitgegeven op of na de datum van 1
        juni, dan treedt zij in werking met ingang van de dag na de
        datum van uitgifte van dat Staatsblad en werkt zij terug tot en
        met 1 juni van het onderhavige begrotingsjaar.</al>
</artikel>
        </wettekst>
        <wetsluiting status="goed">
    <slotformulering>
        <al>Lasten en bevelen dat deze in het Staatsblad zal worden
            geplaatst en dat alle ministeries, autoriteiten, colleges en
            ambtenaren wie zulks aangaat, aan de nauwkeurige uitvoering
            de hand zullen houden.</al>
    </slotformulering>
    <gegeven>
        <dagtekening>
            <plaats>Gegeven te 's-Gravenhage</plaats>
            <datum isodatum="">27 september 2001</datum>
        </dagtekening>
        <koning>Beatrix</koning>
    </gegeven>
    <ondertekening>
        <functie>De Minister van Economische Zaken,</functie>
        <naam>
            <achternaam>A. Jorritsma-Lebbink</achternaam>
        </naam>
    </ondertekening>
    <ondertekening>
        <functie>De Minister van Financi&#xEB;n,</functie>
        <naam>
            <achternaam>G. Zalm</achternaam>
        </naam>
    </ondertekening>
    <uitgifte>
        <datum isodatum="">drie&#xEB;ntwintigste oktober 2001</datum>
        <ondertekening>
            <functie>De Minister van Justitie,</functie>
            <naam>
                <achternaam>A. H. Korthals</achternaam>
            </naam>
        </ondertekening>
    </uitgifte>
</wetsluiting>
        <bijlage status="goed">
    <kop>
        <titel status="officieel">Wijziging van de begroting van de
            uitgaven en de ontvangsten van het Fonds economische
            structuurversterking voor het jaar 2001 (wijziging
            samenhangende met de Voorjaarsnota)</titel>
    </kop>
    <al>Begrotingsstaat behorende bij de Wet van 27 september 2001, Stb. 473</al>
    <al>Begroting 2001</al>
    <al>Fonds economische structuurversterking</al>
    <al>Onderdeel uitgaven</al>
    <table colsep="0" frame="all" orient="port" rowsep="0">
        <tgroup align="left" charoff="75" cols="7" colsep="0" rowsep="0" tgroupstyle="sdu">
            <colspec colname="1" colnum="1" colsep="0" colwidth="0.20in"/>
            <colspec colname="2" colnum="2" colsep="0" colwidth="0.20in"/>
            <colspec colname="3" colnum="3" colsep="0" colwidth="1.61in"/>
            <colspec colname="4" colnum="4" colsep="0" colwidth="1.18in"/>
            <colspec colname="5" colnum="5" colsep="0" colwidth="1.18in"/>
            <colspec colname="6" colnum="6" colsep="0" colwidth="1.18in"/>
            <colspec colname="7" colnum="7" colsep="0" colwidth="1.18in"/>
            <thead valign="bottom">
                <row rowsep="1" valign="top">
                    <entry colname="1" colsep="1" morerows="0" rotate="0" rowsep="1"/>
                    <entry colname="2" colsep="1" morerows="0" rotate="0" rowsep="1"/>
                    <entry colname="3" colsep="1" morerows="0" rotate="0" rowsep="1"/>
                    <entry colsep="1" morerows="0" nameend="5" namest="4" rotate="0" rowsep="1">
                        <al>(1)</al>
                    </entry>
                    <entry morerows="0" nameend="7" namest="6" rotate="0" rowsep="1">
                        <al>(2)</al>
                    </entry>
                </row>
            </thead>
            <tbody valign="bottom">
                <row rowsep="0" valign="top">
                    <entry colname="1" colsep="1" morerows="0" rotate="0" rowsep="1" valign="top">
                        <al>Art.</al>
                    </entry>
                    <entry colname="2" colsep="1" morerows="0" rotate="0" rowsep="1" valign="top"/>
                    <entry colname="3" colsep="1" morerows="0" rotate="0" rowsep="1" valign="top">
                        <al>Omschrijving</al>
                    </entry>
                    <entry colsep="1" morerows="0" nameend="5" namest="4" rotate="0" rowsep="1" valign="top">
                        <al>Oorspronkelijk vastgestelde begroting</al>
                    </entry>
                    <entry morerows="0" nameend="7" namest="6" rotate="0" rowsep="1" valign="top">
                        <al>Mutaties (+ of &#x2013;) op grond van eerste
                            suppletore begroting</al>
                    </entry>
                </row>
                <row rowsep="0" valign="top">
                    <entry colname="1" colsep="1" morerows="0" rotate="0" rowsep="1"/>
                    <entry colname="2" colsep="1" morerows="0" rotate="0" rowsep="1"/>
                    <entry colname="3" colsep="1" morerows="0" rotate="0" rowsep="1"/>
                    <entry align="right" colsep="1" morerows="0" nameend="5" namest="4" rotate="0" rowsep="1">
                        <al>uitgaven</al>
                    </entry>
                    <entry align="right" morerows="0" nameend="7" namest="6" rotate="0" rowsep="1">
                        <al>uitgaven</al>
                    </entry>
                </row>
                <row rowsep="0" valign="top">
                    <entry colname="1" colsep="1" morerows="0" rotate="0" rowsep="1"/>
                    <entry colname="2" colsep="1" morerows="0" rotate="0" rowsep="1"/>
                    <entry colname="3" colsep="1" morerows="0" rotate="0" rowsep="1"/>
                    <entry align="right" colname="4" colsep="1" morerows="0" rotate="0" rowsep="1">
                        <al>NLG1000</al>
                    </entry>
                    <entry align="right" colname="5" colsep="1" morerows="0" rotate="0" rowsep="1">
                        <al>EUR1000</al>
                    </entry>
                    <entry align="right" colname="6" colsep="1" morerows="0" rotate="0" rowsep="1">
                        <al>NLG1000</al>
                    </entry>
                    <entry align="right" colname="7" morerows="0" rotate="0" rowsep="1">
                        <al>EUR1000</al>
                    </entry>
                </row>
                <row rowsep="0" valign="top">
                    <entry colname="1" colsep="1" morerows="0" rotate="0" rowsep="1" valign="top">
                        <al>
                            <nadruk type="vet">01</nadruk>
                        </al>
                    </entry>
                    <entry colname="2" colsep="1" morerows="0" rotate="0" rowsep="1"/>
                    <entry colname="3" colsep="1" morerows="0" rotate="0" rowsep="1">
                        <al>
                            <nadruk type="vet">Bijdragen van het fonds
                                aan andere begrotingen</nadruk>
                        </al>
                    </entry>
                    <entry align="right" colname="4" colsep="1" morerows="0" rotate="0" rowsep="1"/>
                    <entry align="right" colname="5" colsep="1" morerows="0" rotate="0" rowsep="1"/>
                    <entry align="right" colname="6" colsep="1" morerows="0" rotate="0" rowsep="1"/>
                    <entry align="right" colname="7" morerows="0" rotate="0" rowsep="1"/>
                </row>
                <row rowsep="0" valign="top">
                    <entry colname="1" colsep="1" morerows="0" rotate="0" rowsep="1" valign="top"/>
                    <entry colname="2" colsep="1" morerows="0" rotate="0" rowsep="1" valign="top">
                        <al>01</al>
                    </entry>
                    <entry colname="3" colsep="1" morerows="0" rotate="0" rowsep="1">
                        <al>Bijdragen aan de begroting van het
                            Infrastructuurfonds in het kader van verkeer
                            &amp; vervoer</al>
                    </entry>
                    <entry align="right" colname="4" colsep="1" morerows="0" rotate="0" rowsep="1">
                        <al>324&#xA0;095</al>
                    </entry>
                    <entry align="right" colname="5" colsep="1" morerows="0" rotate="0" rowsep="1">
                        <al>147&#xA0;068</al>
                    </entry>
                    <entry align="right" colname="6" colsep="1" morerows="0" rotate="0" rowsep="1">
                        <al>14&#xA0;404</al>
                    </entry>
                    <entry align="right" colname="7" morerows="0" rotate="0" rowsep="1">
                        <al>6&#xA0;536</al>
                    </entry>
                </row>
                <row rowsep="0" valign="top">
                    <entry colname="1" colsep="1" morerows="0" rotate="0" rowsep="1" valign="top"/>
                    <entry colname="2" colsep="1" morerows="0" rotate="0" rowsep="1" valign="top">
                        <al>02</al>
                    </entry>
                    <entry colname="3" colsep="1" morerows="0" rotate="0" rowsep="1">
                        <al>Bijdragen aan andere begrotingen in het
                            kader van bodemsanering</al>
                    </entry>
                    <entry align="right" colname="4" colsep="1" morerows="0" rotate="0" rowsep="1">
                        <al>120&#xA0;135</al>
                    </entry>
                    <entry align="right" colname="5" colsep="1" morerows="0" rotate="0" rowsep="1">
                        <al>54&#xA0;515</al>
                    </entry>
                    <entry align="right" colname="6" colsep="1" morerows="0" rotate="0" rowsep="1">
                        <al>45&#xA0;549</al>
                    </entry>
                    <entry align="right" colname="7" morerows="0" rotate="0" rowsep="1">
                        <al>20&#xA0;669</al>
                    </entry>
                </row>
                <row rowsep="0" valign="top">
                    <entry colname="1" colsep="1" morerows="0" rotate="0" rowsep="1" valign="top"/>
                    <entry colname="2" colsep="1" morerows="0" rotate="0" rowsep="1" valign="top">
                        <al>04</al>
                    </entry>
                    <entry colname="3" colsep="1" morerows="0" rotate="0" rowsep="1">
                        <al>Overige bijdragen vanuit het fonds</al>
                    </entry>
                    <entry align="right" colname="4" colsep="1" morerows="0" rotate="0" rowsep="1">
                        <al>1&#xA0;945&#xA0;000</al>
                    </entry>
                    <entry align="right" colname="5" colsep="1" morerows="0" rotate="0" rowsep="1">
                        <al>882&#xA0;603</al>
                    </entry>
                    <entry align="right" colname="6" colsep="1" morerows="0" rotate="0" rowsep="1"/>
                    <entry align="right" colname="7" morerows="0" rotate="0" rowsep="1"/>
                </row>
                <row rowsep="0" valign="top">
                    <entry colname="1" colsep="1" morerows="0" rotate="0" rowsep="1" valign="top"/>
                    <entry colname="2" colsep="1" morerows="0" rotate="0" rowsep="1" valign="top">
                        <al>07</al>
                    </entry>
                    <entry colname="3" colsep="1" morerows="0" rotate="0" rowsep="1">
                        <al>Projecten in voorbereiding</al>
                    </entry>
                    <entry align="right" colname="4" colsep="1" morerows="0" rotate="0" rowsep="1">
                        <al>76&#xA0;033</al>
                    </entry>
                    <entry align="right" colname="5" colsep="1" morerows="0" rotate="0" rowsep="1">
                        <al>34&#xA0;502</al>
                    </entry>
                    <entry align="right" colname="6" colsep="1" morerows="0" rotate="0" rowsep="1">
                        <al>45&#xA0;217</al>
                    </entry>
                    <entry align="right" colname="7" morerows="0" rotate="0" rowsep="1">
                        <al>20&#xA0;519</al>
                    </entry>
                </row>
                <row rowsep="0" valign="top">
                    <entry colname="1" colsep="1" morerows="0" rotate="0" rowsep="1" valign="top"/>
                    <entry colname="2" colsep="1" morerows="0" rotate="0" rowsep="1" valign="top">
                        <al>08</al>
                    </entry>
                    <entry colname="3" colsep="1" morerows="0" rotate="0" rowsep="1">
                        <al>Investeringsimpuls 1998</al>
                    </entry>
                    <entry align="right" colname="4" colsep="1" morerows="0" rotate="0" rowsep="1">
                        <al>1&#xA0;253&#xA0;285</al>
                    </entry>
                    <entry align="right" colname="5" colsep="1" morerows="0" rotate="0" rowsep="1">
                        <al>568&#xA0;716</al>
                    </entry>
                    <entry align="right" colname="6" colsep="1" morerows="0" rotate="0" rowsep="1">
                        <al>58&#xA0;366</al>
                    </entry>
                    <entry align="right" colname="7" morerows="0" rotate="0" rowsep="1">
                        <al>26&#xA0;485</al>
                    </entry>
                </row>
                <row rowsep="0" valign="top">
                    <entry colname="1" colsep="1" morerows="0" rotate="0" rowsep="1" valign="top"/>
                    <entry colname="2" colsep="1" morerows="0" rotate="0" rowsep="1" valign="top">
                        <al>09</al>
                    </entry>
                    <entry colname="3" colsep="1" morerows="0" rotate="0" rowsep="1">
                        <al>Investeringsimpuls 2001</al>
                    </entry>
                    <entry align="right" colname="4" colsep="1" morerows="0" rotate="0" rowsep="1">
                        <al>1&#xA0;211&#xA0;723</al>
                    </entry>
                    <entry align="right" colname="5" colsep="1" morerows="0" rotate="0" rowsep="1">
                        <al>549&#xA0;856</al>
                    </entry>
                    <entry align="right" colname="6" colsep="1" morerows="0" rotate="0" rowsep="1">
                        <al>606&#xA0;528</al>
                    </entry>
                    <entry align="right" colname="7" morerows="0" rotate="0" rowsep="1">
                        <al>275&#xA0;230</al>
                    </entry>
                </row>
                <row rowsep="0" valign="top">
                    <entry colname="1" colsep="1" morerows="0" rotate="0" rowsep="1" valign="top"/>
                    <entry colname="2" colsep="1" morerows="0" rotate="0" rowsep="1" valign="top">
                        <al>10</al>
                    </entry>
                    <entry colname="3" colsep="1" morerows="0" rotate="0" rowsep="1">
                        <al>Prijsbijstelling</al>
                    </entry>
                    <entry align="right" colname="4" colsep="1" morerows="0" rotate="0" rowsep="1"/>
                    <entry align="right" colname="5" colsep="1" morerows="0" rotate="0" rowsep="1"/>
                    <entry align="right" colname="6" colsep="1" morerows="0" rotate="0" rowsep="1"/>
                    <entry align="right" colname="7" morerows="0" rotate="0" rowsep="1"/>
                </row>
                <row rowsep="0" valign="top">
                    <entry colname="1" colsep="1" morerows="0" rotate="0" rowsep="1" valign="top"/>
                    <entry colname="2" colsep="1" morerows="0" rotate="0" rowsep="1" valign="top"/>
                    <entry colname="3" colsep="1" morerows="0" rotate="0" rowsep="1"/>
                    <entry align="right" colname="4" colsep="1" morerows="0" rotate="0" rowsep="1"/>
                    <entry align="right" colname="5" colsep="1" morerows="0" rotate="0" rowsep="1"/>
                    <entry align="right" colname="6" colsep="1" morerows="0" rotate="0" rowsep="1"/>
                    <entry align="right" colname="7" morerows="0" rotate="0" rowsep="1"/>
                </row>
                <row rowsep="0" valign="top">
                    <entry colname="1" colsep="1" morerows="0" rotate="0" rowsep="1" valign="top"/>
                    <entry colname="2" colsep="1" morerows="0" rotate="0" rowsep="1" valign="top"/>
                    <entry colname="3" colsep="1" morerows="0" rotate="0" rowsep="1">
                        <al>
                            <nadruk type="vet">Sub-totaal uitgaven</nadruk>
                        </al>
                    </entry>
                    <entry align="right" colname="4" colsep="1" morerows="0" rotate="0" rowsep="1">
                        <al>
                            <nadruk type="vet">4&#xA0;930&#xA0;271</nadruk>
                        </al>
                    </entry>
                    <entry align="right" colname="5" colsep="1" morerows="0" rotate="0" rowsep="1">
                        <al>
                            <nadruk type="vet">2&#xA0;237&#xA0;259</nadruk>
                        </al>
                    </entry>
                    <entry align="right" colname="6" colsep="1" morerows="0" rotate="0" rowsep="1">
                        <al>
                            <nadruk type="vet">770&#xA0;064</nadruk>
                        </al>
                    </entry>
                    <entry align="right" colname="7" morerows="0" rotate="0" rowsep="1">
                        <al>
                            <nadruk type="vet">349&#xA0;440</nadruk>
                        </al>
                    </entry>
                </row>
                <row rowsep="0" valign="top">
                    <entry colname="1" colsep="1" morerows="0" rotate="0" rowsep="1" valign="top"/>
                    <entry colname="2" colsep="1" morerows="0" rotate="0" rowsep="1" valign="top"/>
                    <entry colname="3" colsep="1" morerows="0" rotate="0" rowsep="1"/>
                    <entry align="right" colname="4" colsep="1" morerows="0" rotate="0" rowsep="1"/>
                    <entry align="right" colname="5" colsep="1" morerows="0" rotate="0" rowsep="1"/>
                    <entry align="right" colname="6" colsep="1" morerows="0" rotate="0" rowsep="1"/>
                    <entry align="right" colname="7" morerows="0" rotate="0" rowsep="1"/>
                </row>
                <row rowsep="0" valign="top">
                    <entry colname="1" colsep="1" morerows="0" rotate="0" rowsep="1" valign="top">
                        <al>
                            <nadruk type="vet">02</nadruk>
                        </al>
                    </entry>
                    <entry colname="2" colsep="1" morerows="0" rotate="0" rowsep="1" valign="top"/>
                    <entry colname="3" colsep="1" morerows="0" rotate="0" rowsep="1">
                        <al>
                            <nadruk type="vet">Saldi</nadruk>
                        </al>
                    </entry>
                    <entry align="right" colname="4" colsep="1" morerows="0" rotate="0" rowsep="1"/>
                    <entry align="right" colname="5" colsep="1" morerows="0" rotate="0" rowsep="1"/>
                    <entry align="right" colname="6" colsep="1" morerows="0" rotate="0" rowsep="1"/>
                    <entry align="right" colname="7" morerows="0" rotate="0" rowsep="1"/>
                </row>
                <row rowsep="0" valign="top">
                    <entry colname="1" colsep="1" morerows="0" rotate="0" rowsep="1" valign="top"/>
                    <entry colname="2" colsep="1" morerows="0" rotate="0" rowsep="1" valign="top">
                        <al>01</al>
                    </entry>
                    <entry colname="3" colsep="1" morerows="0" rotate="0" rowsep="1">
                        <al>Voordelig eindsaldo</al>
                    </entry>
                    <entry align="right" colname="4" colsep="1" morerows="0" rotate="0" rowsep="1">
                        <al>3&#xA0;279&#xA0;712</al>
                    </entry>
                    <entry align="right" colname="5" colsep="1" morerows="0" rotate="0" rowsep="1">
                        <al>1&#xA0;488&#xA0;268</al>
                    </entry>
                    <entry align="right" colname="6" colsep="1" morerows="0" rotate="0" rowsep="1">
                        <al>116&#xA0;019</al>
                    </entry>
                    <entry align="right" colname="7" morerows="0" rotate="0" rowsep="1">
                        <al>52&#xA0;647</al>
                    </entry>
                </row>
                <row rowsep="0" valign="top">
                    <entry colname="1" colsep="1" morerows="0" rotate="0" rowsep="1" valign="top"/>
                    <entry colname="2" colsep="1" morerows="0" rotate="0" rowsep="1" valign="top"/>
                    <entry colname="3" colsep="1" morerows="0" rotate="0" rowsep="1"/>
                    <entry align="right" colname="4" colsep="1" morerows="0" rotate="0" rowsep="1"/>
                    <entry align="right" colname="5" colsep="1" morerows="0" rotate="0" rowsep="1"/>
                    <entry align="right" colname="6" colsep="1" morerows="0" rotate="0" rowsep="1"/>
                    <entry align="right" colname="7" morerows="0" rotate="0" rowsep="1"/>
                </row>
                <row rowsep="0" valign="top">
                    <entry colname="1" colsep="1" morerows="0" rotate="0" rowsep="1" valign="top"/>
                    <entry colname="2" colsep="1" morerows="0" rotate="0" rowsep="1" valign="top"/>
                    <entry colname="3" colsep="1" morerows="0" rotate="0" rowsep="1">
                        <al>
                            <nadruk type="vet">Sub-totaal</nadruk>
                        </al>
                    </entry>
                    <entry align="right" colname="4" colsep="1" morerows="0" rotate="0" rowsep="1">
                        <al>
                            <nadruk type="vet">3&#xA0;279&#xA0;712</nadruk>
                        </al>
                    </entry>
                    <entry align="right" colname="5" colsep="1" morerows="0" rotate="0" rowsep="1">
                        <al>
                            <nadruk type="vet">1&#xA0;488&#xA0;268</nadruk>
                        </al>
                    </entry>
                    <entry align="right" colname="6" colsep="1" morerows="0" rotate="0" rowsep="1">
                        <al>
                            <nadruk type="vet">116&#xA0;019</nadruk>
                        </al>
                    </entry>
                    <entry align="right" colname="7" morerows="0" rotate="0" rowsep="1">
                        <al>
                            <nadruk type="vet">52&#xA0;647</nadruk>
                        </al>
                    </entry>
                </row>
                <row rowsep="0" valign="top">
                    <entry colname="1" colsep="1" morerows="0" rotate="0" rowsep="1" valign="top"/>
                    <entry colname="2" colsep="1" morerows="0" rotate="0" rowsep="1" valign="top"/>
                    <entry colname="3" colsep="1" morerows="0" rotate="0" rowsep="1"/>
                    <entry align="right" colname="4" colsep="1" morerows="0" rotate="0" rowsep="1"/>
                    <entry align="right" colname="5" colsep="1" morerows="0" rotate="0" rowsep="1"/>
                    <entry align="right" colname="6" colsep="1" morerows="0" rotate="0" rowsep="1"/>
                    <entry align="right" colname="7" morerows="0" rotate="0" rowsep="1"/>
                </row>
                <row rowsep="0" valign="top">
                    <entry colname="1" colsep="1" morerows="0" rotate="0" valign="top"/>
                    <entry colname="2" colsep="1" morerows="0" rotate="0" valign="top"/>
                    <entry colname="3" colsep="1" morerows="0" rotate="0">
                        <al>
                            <nadruk type="vet">Totaaltelling</nadruk>
                        </al>
                    </entry>
                    <entry align="right" colname="4" colsep="1" morerows="0" rotate="0">
                        <al>
                            <nadruk type="vet">8&#xA0;209&#xA0;983</nadruk>
                        </al>
                    </entry>
                    <entry align="right" colname="5" colsep="1" morerows="0" rotate="0">
                        <al>
                            <nadruk type="vet">3&#xA0;725&#xA0;528</nadruk>
                        </al>
                    </entry>
                    <entry align="right" colname="6" colsep="1" morerows="0" rotate="0">
                        <al>
                            <nadruk type="vet">886&#xA0;083</nadruk>
                        </al>
                    </entry>
                    <entry align="right" colname="7" morerows="0" rotate="0">
                        <al>
                            <nadruk type="vet">402&#xA0;087</nadruk>
                        </al>
                    </entry>
                </row>
            </tbody>
        </tgroup>
    </table>
    <al/>
    <al>Ons bekend,</al>
    <al>De Minister van Economische Zaken,</al>
    <al>A. Jorritsma-Lebbink</al>
    <al>De Minister van Financi&#xEB;n,</al>
    <al>G. Zalm </al>
</bijlage>
        <bijlage status="goed">
    <kop>
        <titel status="officieel">Wijziging van de begroting van de
            uitgaven en de ontvangsten van het Fonds economische
            structuurversterking voor het jaar 2001 (wijziging
            samenhangende met de Voorjaarsnota)</titel>
    </kop>
    <al>Begrotingsstaat behorende bij de Wet van 27 september 2001, Stb. 473</al>
    <al>Begroting 2001</al>
    <al>Fonds economische structuurversterking</al>
    <al>Onderdeel ontvangsten</al>
    <table colsep="0" frame="all" orient="port" rowsep="0">
        <tgroup align="left" charoff="75" cols="7" colsep="0" rowsep="0" tgroupstyle="sdu">
            <colspec colname="1" colnum="1" colsep="0" colwidth="0.20in"/>
            <colspec colname="2" colnum="2" colsep="0" colwidth="0.20in"/>
            <colspec colname="3" colnum="3" colsep="0" colwidth="1.61in"/>
            <colspec colname="4" colnum="4" colsep="0" colwidth="1.18in"/>
            <colspec colname="5" colnum="5" colsep="0" colwidth="1.18in"/>
            <colspec colname="6" colnum="6" colsep="0" colwidth="1.18in"/>
            <colspec colname="7" colnum="7" colsep="0" colwidth="1.18in"/>
            <thead valign="bottom">
                <row rowsep="1" valign="top">
                    <entry colname="1" colsep="1" morerows="0" rotate="0" rowsep="1"/>
                    <entry colname="2" colsep="1" morerows="0" rotate="0" rowsep="1"/>
                    <entry colname="3" colsep="1" morerows="0" rotate="0" rowsep="1"/>
                    <entry colsep="1" morerows="0" nameend="5" namest="4" rotate="0" rowsep="1">
                        <al>(1)</al>
                    </entry>
                    <entry morerows="0" nameend="7" namest="6" rotate="0" rowsep="1">
                        <al>(2)</al>
                    </entry>
                </row>
            </thead>
            <tbody valign="bottom">
                <row rowsep="0" valign="top">
                    <entry colname="1" colsep="1" morerows="0" rotate="0" rowsep="1" valign="top">
                        <al>Art.</al>
                    </entry>
                    <entry colname="2" colsep="1" morerows="0" rotate="0" rowsep="1" valign="top"/>
                    <entry colname="3" colsep="1" morerows="0" rotate="0" rowsep="1" valign="top">
                        <al>Omschrijving</al>
                    </entry>
                    <entry colsep="1" morerows="0" nameend="5" namest="4" rotate="0" rowsep="1" valign="top">
                        <al>Oorspronkelijk vastgestelde begroting</al>
                    </entry>
                    <entry morerows="0" nameend="7" namest="6" rotate="0" rowsep="1" valign="top">
                        <al>Mutaties (+ of &#x2013;) op grond van eerste
                            suppletore begroting</al>
                    </entry>
                </row>
                <row rowsep="0" valign="top">
                    <entry colname="1" colsep="1" morerows="0" rotate="0" rowsep="1"/>
                    <entry colname="2" colsep="1" morerows="0" rotate="0" rowsep="1"/>
                    <entry colname="3" colsep="1" morerows="0" rotate="0" rowsep="1"/>
                    <entry align="right" colsep="1" morerows="0" nameend="5" namest="4" rotate="0" rowsep="1">
                        <al>ontvangsten</al>
                    </entry>
                    <entry align="right" morerows="0" nameend="7" namest="6" rotate="0" rowsep="1">
                        <al>ontvangsten</al>
                    </entry>
                </row>
                <row rowsep="0" valign="top">
                    <entry colname="1" colsep="1" morerows="0" rotate="0" rowsep="1"/>
                    <entry colname="2" colsep="1" morerows="0" rotate="0" rowsep="1"/>
                    <entry colname="3" colsep="1" morerows="0" rotate="0" rowsep="1"/>
                    <entry align="right" colname="4" colsep="1" morerows="0" rotate="0" rowsep="1">
                        <al>NLG1000</al>
                    </entry>
                    <entry align="right" colname="5" colsep="1" morerows="0" rotate="0" rowsep="1">
                        <al>EUR1000</al>
                    </entry>
                    <entry align="right" colname="6" colsep="1" morerows="0" rotate="0" rowsep="1">
                        <al>NLG1000</al>
                    </entry>
                    <entry align="right" colname="7" morerows="0" rotate="0" rowsep="1">
                        <al>EUR1000</al>
                    </entry>
                </row>
                <row rowsep="0" valign="top">
                    <entry colname="1" colsep="1" morerows="0" rotate="0" rowsep="1" valign="top">
                        <al>
                            <nadruk type="vet">01</nadruk>
                        </al>
                    </entry>
                    <entry colname="2" colsep="1" morerows="0" rotate="0" rowsep="1" valign="top">
                        <al>
                            <nadruk type="vet"/>
                        </al>
                    </entry>
                    <entry colname="3" colsep="1" morerows="0" rotate="0" rowsep="1">
                        <al>
                            <nadruk type="vet">Ontvangsten van het fonds</nadruk>
                        </al>
                    </entry>
                    <entry align="right" colname="4" colsep="1" morerows="0" rotate="0" rowsep="1"/>
                    <entry align="right" colname="5" colsep="1" morerows="0" rotate="0" rowsep="1"/>
                    <entry align="right" colname="6" colsep="1" morerows="0" rotate="0" rowsep="1"/>
                    <entry align="right" colname="7" morerows="0" rotate="0" rowsep="1"/>
                </row>
                <row rowsep="0" valign="top">
                    <entry colname="1" colsep="1" morerows="0" rotate="0" rowsep="1" valign="top"/>
                    <entry colname="2" colsep="1" morerows="0" rotate="0" rowsep="1" valign="top">
                        <al>03</al>
                    </entry>
                    <entry colname="3" colsep="1" morerows="0" rotate="0" rowsep="1">
                        <al>Overige ontvangsten uit aardgas</al>
                    </entry>
                    <entry align="right" colname="4" colsep="1" morerows="0" rotate="0" rowsep="1">
                        <al>2&#xA0;864&#xA0;000</al>
                    </entry>
                    <entry align="right" colname="5" colsep="1" morerows="0" rotate="0" rowsep="1">
                        <al>1&#xA0;299&#xA0;627</al>
                    </entry>
                    <entry align="right" colname="6" colsep="1" morerows="0" rotate="0" rowsep="1">
                        <al>332&#xA0;000</al>
                    </entry>
                    <entry align="right" colname="7" morerows="0" rotate="0" rowsep="1">
                        <al>150&#xA0;655</al>
                    </entry>
                </row>
                <row rowsep="0" valign="top">
                    <entry colname="1" colsep="1" morerows="0" rotate="0" rowsep="1" valign="top"/>
                    <entry colname="2" colsep="1" morerows="0" rotate="0" rowsep="1" valign="top">
                        <al>06</al>
                    </entry>
                    <entry colname="3" colsep="1" morerows="0" rotate="0" rowsep="1">
                        <al>Rentebesparingen uit incidentele baten</al>
                    </entry>
                    <entry align="right" colname="4" colsep="1" morerows="0" rotate="0" rowsep="1">
                        <al>746&#xA0;621</al>
                    </entry>
                    <entry align="right" colname="5" colsep="1" morerows="0" rotate="0" rowsep="1">
                        <al>338&#xA0;802</al>
                    </entry>
                    <entry align="right" colname="6" colsep="1" morerows="0" rotate="0" rowsep="1">
                        <al>106&#xA0;100</al>
                    </entry>
                    <entry align="right" colname="7" morerows="0" rotate="0" rowsep="1">
                        <al>48&#xA0;146</al>
                    </entry>
                </row>
                <row rowsep="0" valign="top">
                    <entry colname="1" colsep="1" morerows="0" rotate="0" rowsep="1" valign="top"/>
                    <entry colname="2" colsep="1" morerows="0" rotate="0" rowsep="1" valign="top">
                        <al>07</al>
                    </entry>
                    <entry colname="3" colsep="1" morerows="0" rotate="0" rowsep="1">
                        <al>Overige ontvangsten</al>
                    </entry>
                    <entry align="right" colname="4" colsep="1" morerows="0" rotate="0" rowsep="1"/>
                    <entry align="right" colname="5" colsep="1" morerows="0" rotate="0" rowsep="1"/>
                    <entry align="right" colname="6" colsep="1" morerows="0" rotate="0" rowsep="1"/>
                    <entry align="right" colname="7" morerows="0" rotate="0" rowsep="1"/>
                </row>
                <row rowsep="0" valign="top">
                    <entry colname="1" colsep="1" morerows="0" rotate="0" rowsep="1" valign="top"/>
                    <entry colname="2" colsep="1" morerows="0" rotate="0" rowsep="1" valign="top"/>
                    <entry colname="3" colsep="1" morerows="0" rotate="0" rowsep="1"/>
                    <entry align="right" colname="4" colsep="1" morerows="0" rotate="0" rowsep="1"/>
                    <entry align="right" colname="5" colsep="1" morerows="0" rotate="0" rowsep="1"/>
                    <entry align="right" colname="6" colsep="1" morerows="0" rotate="0" rowsep="1"/>
                    <entry align="right" colname="7" morerows="0" rotate="0" rowsep="1"/>
                </row>
                <row rowsep="0" valign="top">
                    <entry colname="1" colsep="1" morerows="0" rotate="0" rowsep="1" valign="top"/>
                    <entry colname="2" colsep="1" morerows="0" rotate="0" rowsep="1" valign="top"/>
                    <entry colname="3" colsep="1" morerows="0" rotate="0" rowsep="1">
                        <al>
                            <nadruk type="vet">Sub-totaal ontvangsten</nadruk>
                        </al>
                    </entry>
                    <entry align="right" colname="4" colsep="1" morerows="0" rotate="0" rowsep="1">
                        <al>
                            <nadruk type="vet">3&#xA0;610&#xA0;621</nadruk>
                        </al>
                    </entry>
                    <entry align="right" colname="5" colsep="1" morerows="0" rotate="0" rowsep="1">
                        <al>
                            <nadruk type="vet">1&#xA0;638&#xA0;428</nadruk>
                        </al>
                    </entry>
                    <entry align="right" colname="6" colsep="1" morerows="0" rotate="0" rowsep="1">
                        <al>
                            <nadruk type="vet">438&#xA0;100</nadruk>
                        </al>
                    </entry>
                    <entry align="right" colname="7" morerows="0" rotate="0" rowsep="1">
                        <al>
                            <nadruk type="vet">198&#xA0;801</nadruk>
                        </al>
                    </entry>
                </row>
                <row rowsep="0" valign="top">
                    <entry colname="1" colsep="1" morerows="0" rotate="0" rowsep="1" valign="top"/>
                    <entry colname="2" colsep="1" morerows="0" rotate="0" rowsep="1" valign="top"/>
                    <entry colname="3" colsep="1" morerows="0" rotate="0" rowsep="1"/>
                    <entry align="right" colname="4" colsep="1" morerows="0" rotate="0" rowsep="1"/>
                    <entry align="right" colname="5" colsep="1" morerows="0" rotate="0" rowsep="1"/>
                    <entry align="right" colname="6" colsep="1" morerows="0" rotate="0" rowsep="1"/>
                    <entry align="right" colname="7" morerows="0" rotate="0" rowsep="1"/>
                </row>
                <row rowsep="0" valign="top">
                    <entry colname="1" colsep="1" morerows="0" rotate="0" rowsep="1" valign="top">
                        <al>
                            <nadruk type="vet">02</nadruk>
                        </al>
                    </entry>
                    <entry colname="2" colsep="1" morerows="0" rotate="0" rowsep="1" valign="top"/>
                    <entry colname="3" colsep="1" morerows="0" rotate="0" rowsep="1">
                        <al>
                            <nadruk type="vet">Saldi</nadruk>
                        </al>
                    </entry>
                    <entry align="right" colname="4" colsep="1" morerows="0" rotate="0" rowsep="1"/>
                    <entry align="right" colname="5" colsep="1" morerows="0" rotate="0" rowsep="1"/>
                    <entry align="right" colname="6" colsep="1" morerows="0" rotate="0" rowsep="1"/>
                    <entry align="right" colname="7" morerows="0" rotate="0" rowsep="1"/>
                </row>
                <row rowsep="0" valign="top">
                    <entry colname="1" colsep="1" morerows="0" rotate="0" rowsep="1" valign="top"/>
                    <entry colname="2" colsep="1" morerows="0" rotate="0" rowsep="1" valign="top">
                        <al>01</al>
                    </entry>
                    <entry colname="3" colsep="1" morerows="0" rotate="0" rowsep="1">
                        <al>Voordelig beginsaldo</al>
                    </entry>
                    <entry align="right" colname="4" colsep="1" morerows="0" rotate="0" rowsep="1">
                        <al>4&#xA0;649&#xA0;362</al>
                    </entry>
                    <entry align="right" colname="5" colsep="1" morerows="0" rotate="0" rowsep="1">
                        <al>2&#xA0;109&#xA0;788</al>
                    </entry>
                    <entry align="right" colname="6" colsep="1" morerows="0" rotate="0" rowsep="1">
                        <al>397&#xA0;983</al>
                    </entry>
                    <entry align="right" colname="7" morerows="0" rotate="0" rowsep="1">
                        <al>180&#xA0;597</al>
                    </entry>
                </row>
                <row rowsep="0" valign="top">
                    <entry colname="1" colsep="1" morerows="0" rotate="0" rowsep="1" valign="top"/>
                    <entry colname="2" colsep="1" morerows="0" rotate="0" rowsep="1" valign="top"/>
                    <entry colname="3" colsep="1" morerows="0" rotate="0" rowsep="1"/>
                    <entry align="right" colname="4" colsep="1" morerows="0" rotate="0" rowsep="1"/>
                    <entry align="right" colname="5" colsep="1" morerows="0" rotate="0" rowsep="1"/>
                    <entry align="right" colname="6" colsep="1" morerows="0" rotate="0" rowsep="1"/>
                    <entry align="right" colname="7" morerows="0" rotate="0" rowsep="1"/>
                </row>
                <row rowsep="0" valign="top">
                    <entry colname="1" colsep="1" morerows="0" rotate="0" rowsep="1" valign="top"/>
                    <entry colname="2" colsep="1" morerows="0" rotate="0" rowsep="1" valign="top"/>
                    <entry colname="3" colsep="1" morerows="0" rotate="0" rowsep="1">
                        <al>
                            <nadruk type="vet">Sub-totaal</nadruk>
                        </al>
                    </entry>
                    <entry align="right" colname="4" colsep="1" morerows="0" rotate="0" rowsep="1">
                        <al>
                            <nadruk type="vet">4&#xA0;649&#xA0;362</nadruk>
                        </al>
                    </entry>
                    <entry align="right" colname="5" colsep="1" morerows="0" rotate="0" rowsep="1">
                        <al>
                            <nadruk type="vet">2&#xA0;109&#xA0;788</nadruk>
                        </al>
                    </entry>
                    <entry align="right" colname="6" colsep="1" morerows="0" rotate="0" rowsep="1">
                        <al>
                            <nadruk type="vet">397&#xA0;983</nadruk>
                        </al>
                    </entry>
                    <entry align="right" colname="7" morerows="0" rotate="0" rowsep="1">
                        <al>
                            <nadruk type="vet">180&#xA0;597</nadruk>
                        </al>
                    </entry>
                </row>
                <row rowsep="0" valign="top">
                    <entry colname="1" colsep="1" morerows="0" rotate="0" rowsep="1" valign="top"/>
                    <entry colname="2" colsep="1" morerows="0" rotate="0" rowsep="1" valign="top"/>
                    <entry colname="3" colsep="1" morerows="0" rotate="0" rowsep="1"/>
                    <entry align="right" colname="4" colsep="1" morerows="0" rotate="0" rowsep="1"/>
                    <entry align="right" colname="5" colsep="1" morerows="0" rotate="0" rowsep="1"/>
                    <entry align="right" colname="6" colsep="1" morerows="0" rotate="0" rowsep="1"/>
                    <entry align="right" colname="7" morerows="0" rotate="0" rowsep="1"/>
                </row>
                <row rowsep="0" valign="top">
                    <entry colname="1" colsep="1" morerows="0" rotate="0" valign="top"/>
                    <entry colname="2" colsep="1" morerows="0" rotate="0" valign="top"/>
                    <entry colname="3" colsep="1" morerows="0" rotate="0">
                        <al>
                            <nadruk type="vet">Totaaltelling</nadruk>
                        </al>
                    </entry>
                    <entry align="right" colname="4" colsep="1" morerows="0" rotate="0">
                        <al>
                            <nadruk type="vet">8&#xA0;259&#xA0;983</nadruk>
                        </al>
                    </entry>
                    <entry align="right" colname="5" colsep="1" morerows="0" rotate="0">
                        <al>
                            <nadruk type="vet">3&#xA0;748&#xA0;217</nadruk>
                        </al>
                    </entry>
                    <entry align="right" colname="6" colsep="1" morerows="0" rotate="0">
                        <al>
                            <nadruk type="vet">836&#xA0;083</nadruk>
                        </al>
                    </entry>
                    <entry align="right" colname="7" morerows="0" rotate="0">
                        <al>
                            <nadruk type="vet">379&#xA0;398</nadruk>
                        </al>
                    </entry>
                </row>
            </tbody>
        </tgroup>
    </table>
    <al/>
    <al>Ons bekend,</al>
    <al>De Minister van Economische Zaken,</al>
    <al>A. Jorritsma-Lebbink</al>
    <al>De Minister van Financi&#xEB;n,</al>
    <al>G. Zalm</al>
</bijlage>
    </wet-besluit>
</wetgeving>
  	