<?xml version="1.0"?>
<!DOCTYPE wetgeving SYSTEM "http://wetten.overheid.nl/dtd/bwb-plus-meta-1_61w.dtd">
<wetgeving bwb-id="BWBR0006553" dtdversie="2.0" id="218189" xml:lang="nl" soort="ministeriele-regeling">    <intitule>Regeling van de Minister van Binnenlandse Zaken, nr. EA94/U907,   houdende regels voor de kleding van de politie</intitule>        <regeling>    <aanhef><wie>De Minister van Binnenlandse Zaken,</wie><considerans><considerans.al bevat="overeenstemmend">Handelende in overeenstemming     met de Minister van Justitie;</considerans.al><considerans.al bevat="grondslag">Gelet op artikel <extref status="actief" doc="1.0:v:BWBR0006299&amp;artikel=49" compleet="nee">artikel 49, tweede     lid, van de Politiewet 1993</extref>, <extref status="actief" doc="1.0:v:BWBR0006516&amp;artikel=56" compleet="nee">artikel 56, eerste lid, van het Besluit algemene     rechtspositie politie</extref>;</considerans.al></considerans><afkondiging><al>Besluit:</al></afkondiging></aanhef>    <regeling-tekst>    <artikel status="goed">      <kop>      <label>Artikel</label>      <nr status="officieel">1</nr>      </kop>      <al>In deze regeling wordt verstaan onder:</al>      <definitielijst nr-sluiting="" plaatsing="inline" type="expliciet">     <definitie-item>     <li.nr>a.</li.nr>      <term><nadruk type="cur">uniform:</nadruk></term>      <definitie>        <al> het samenstel van de in <intref status="actief" doc="1.0:v:BWBR0006553&amp;bijlage=1">bijlage 1</intref> genoemde kledingstukken en       de in <intref status="actief" doc="1.0:v:BWBR0006553&amp;bijlage=2">bijlage 2</intref> genoemde uitmonstering;</al>      </definitie>      </definitie-item>     <definitie-item>     <li.nr>b.</li.nr>      <term><nadruk type="cur">dienstkleding:</nadruk></term>      <definitie>        <al> de door de beheerder aan de ambtenaar verstrekte kleding,       niet zijnde het uniform.</al>      </definitie>      </definitie-item>     <definitie-item>     <li.nr>c.</li.nr>      <term><nadruk type="cur">beheerder:</nadruk></term>      <definitie>        <lijst level="single" nr-sluiting="" start="1" type="expliciet">       <li>       <li.nr>1&#xBA;.</li.nr>        <al>voor de regionale politiekorpsen de burgemeester, bedoeld         in <extref status="actief" doc="1.0:v:BWBR0006299&amp;artikel=23" compleet="nee">artikel 23 van de Politiewet 1993</extref>; </al>        </li>       <li>       <li.nr>2&#xBA;.</li.nr>        <al>voor het Korps landelijke politiediensten de Minister van Veiligheid en
Justitie;</al>        </li>       </lijst>      </definitie>      </definitie-item>     <definitie-item>     <li.nr>d.</li.nr>      <term><nadruk type="cur">ambtenaar:</nadruk></term>      <definitie>        <al> de ambtenaren, genoemd in <extref status="actief" doc="1.0:v:BWBR0006516&amp;artikel=56" compleet="nee">artikel 56, eerste lid, van het       Besluit algemene rechtspositie politie</extref> en de vrijwillige ambtenaren van       politie, bedoeld in <extref status="actief" doc="1.0:v:BWBR0007321&amp;artikel=15" compleet="nee">artikel 15 van het Besluit rechtspositie vrijwillige       politie</extref>.</al>      </definitie>      </definitie-item>     </definitielijst>          </artikel>    <artikel status="goed">                     <kop>
                        <label>Artikel</label>
                        <nr status="officieel">2</nr>
                     </kop>
                     <lid>
                        <lidnr status="officieel">1</lidnr>
                        <al>De
beheerder draagt er zorg voor dat het uniform en de dienstkleding
bestaan uit de in <intref status="actief" doc="1.0:v:BWBR0006553&amp;bijlage=1">bijlage 1</intref> genoemde kledingstukken voor de basistaken
en de door de beheerder toegewezen bijzondere
taken.</al>
                     </lid>
                     <lid><lidnr status="officieel">2</lidnr><al>De
ambtenaar is verantwoordelijk voor de reiniging van overhemden/blouses,
poloshirts, sokken en onderkleding. De aan de reiniging verbonden
kosten zijn voor rekening van de
ambtenaar.</al></lid><lid>
                        <lidnr status="officieel">3</lidnr>
                        <al>De
beheerder draagt er zorg voor dat onder de omstandigheden waarin het
nodig is dat de aanwezigheid van de ambtenaar zichtbaar is, deze
ambtenaar een zichtbaarheidsvest, blouson, parka, regenkleding of
regencape als bedoeld in <intref status="actief" doc="1.0:v:BWBR0006553&amp;bijlage=1">bijlage 1</intref>
draagt.</al>
                     </lid>
                  </artikel>    <artikel status="goed">      <kop>      <label>Artikel</label>      <nr>3</nr>      </kop>      <al>De beheerder geeft in een reglement aan:</al>      <lijst nr-sluiting="">     <li>     <li.nr>a.</li.nr>      <al>welke in <intref status="actief" doc="1.0:v:BWBR0006553&amp;bijlage=1">bijlage 1</intref> genoemde kledingstukken en in <intref status="actief" doc="1.0:v:BWBR0006553&amp;bijlage=2">bijlage 2</intref>       genoemde uitmonstering verstrekt worden;</al>      </li>     <li>     <li.nr>b.</li.nr>      <al>de wijze van verstrekking van het uniform;</al>      </li>     <li>     <li.nr>c.</li.nr>      <al>op welke wijze het uniform wordt gedragen met dien verstande       dat het witte overhemd in combinatie met de tuniek wordt gedragen en het blauwe       overhemd in combinatie met de blouson wordt gedragen;</al>      </li>     <li>     <li.nr>d.</li.nr>      <al>op welke wijze het uniform wordt onderhouden.</al>      </li>     </lijst>          </artikel>    <artikel status="goed">      <kop>      <label>Artikel</label>      <nr>4</nr>      </kop>      <lid>      <lidnr>1</lidnr>      <al>Het uniform is eigendom van de regio waar de ambtenaar in dienst     is, dan wel van de Staat indien de ambtenaar werkzaam is bij het Korps     landelijke politiediensten.</al>      </lid>      <lid>      <lidnr>2</lidnr>      <al>De ambtenaar is verantwoordelijk voor het hem verstrekte     uniform.</al>      </lid>          </artikel>    <artikel status="goed">      <kop>      <label>Artikel</label>      <nr>5</nr>      </kop>      <al>Het uniform dat aan de ambtenaar is verstrekt, wordt door de     beheerder ingenomen bij:</al>      <lijst nr-sluiting="">     <li>     <li.nr>a.</li.nr>      <al>de vervanging van het uniform,</al>      </li>     <li>     <li.nr>b.</li.nr>      <al>het overlijden van de ambtenaar, of</al>      </li>     <li>     <li.nr>c.</li.nr>      <al>het ontslag van de ambtenaar uit de politiedienst.</al>      </li>     </lijst>          </artikel>    <artikel status="goed">      <kop>      <label>Artikel</label>      <nr>6</nr>      </kop>      <al>De beheerder draagt er zorg voor dat het uniform niet in handen van     onbevoegden terecht komt.</al>          </artikel>    <artikel status="goed">      <kop>      <label>Artikel</label>      <nr>7</nr>      </kop>      <al>Deze regeling treedt in werking met ingang van 1 april 1994.</al>          </artikel>    <artikel status="goed">      <kop>      <label>Artikel</label>      <nr>8</nr>      </kop>      <al>Deze regeling wordt aangehaald als: Kledingregeling voor de     politie.</al>      <al>Deze regeling zal in de Staatscourant en het Algemeen Politieblad     worden geplaatst met uitzondering van de bijlage 3, die op het ministerie van     Binnenlandse Zaken ter inzage wordt gelegd.</al>          </artikel>    </regeling-tekst>    <regeling-sluiting status="goed">    <gegeven>      <dagtekening>      <plaats>'s-Gravenhage</plaats>      <datum isodatum="1994-03-25">25 maart 1994</datum>      </dagtekening>    </gegeven>    <ondertekenaar>      <ondertekening> De <functie>Minister</functie> van     <organisatie>Binnenlandse Zaken</organisatie>,      <naam>      <voornaam>E. van</voornaam>      <achternaam>Thijn</achternaam>      </naam> </ondertekening>    </ondertekenaar>        </regeling-sluiting>    <bijlage status="goed">    <kop>      <label>Bijlage</label>      <nr status="officieel">1</nr>      <titel status="officieel">behorende bij <intref status="actief" doc="1.0:v:BWBR0006553&amp;artikel=1">artikel 1, onderdeel a</intref>, van de Kledingregeling voor de
politie	
</titel>    </kop>    <divisie opmaak="default"><kop>
                        <titel status="officieel">Kledingstukken</titel>
                     </kop><divisie opmaak="default"><kop>
                           <titel status="officieel">Basisuniformpakket
(heren/dames)</titel>
                        </kop><al>Het pakket bestaat
uit:</al>
                        <lijst level="single" nr-sluiting="." start="1" type="expliciet">
                           <li>
                              <li.nr>&#x2013;</li.nr>
                              <al>blouson</al>
                           </li>
                           <li>
                              <li.nr>&#x2013;</li.nr>
                              <al>bontmuts</al>
                           </li>
                           <li>
                              <li.nr>&#x2013;</li.nr>
                              <al>col</al>
                           </li>
                           <li>
                              <li.nr>&#x2013;</li.nr>
                              <al>colbert</al>
                           </li>
                           <li>
                              <li.nr>&#x2013;</li.nr>
                              <al>dienstonderscheidingstekens</al>
                           </li>
                           <li>
                              <li.nr>&#x2013;</li.nr>
                              <al>halsdoek</al>
                           </li>
                           <li>
                              <li.nr>&#x2013;</li.nr>
                              <al>handschoenen</al>
                           </li>
                           <li>
                              <li.nr>&#x2013;</li.nr>
                              <al>koppel</al>
                           </li>
                           <li>
                              <li.nr>&#x2013;</li.nr>
                              <al>lijfriem</al>
                           </li>
                           <li>
                              <li.nr>&#x2013;</li.nr>
                              <al>naamplaatje</al>
                           </li>
                           <li>
                              <li.nr>&#x2013;</li.nr>
                              <al>overhemd/blouse</al>
                           </li>
                           <li>
                              <li.nr>&#x2013;</li.nr>
                              <al>overjas</al>
                           </li>
                           <li>
                              <li.nr>&#x2013;</li.nr>
                              <al>pantalon/
rok</al>
                           </li>
                           <li>
                              <li.nr>&#x2013;</li.nr>
                              <al>parka</al>
                           </li>
                           <li>
                              <li.nr>&#x2013;</li.nr>
                              <al>pet
/hoed</al>
                           </li>
                           <li>
                              <li.nr>&#x2013;</li.nr>
                              <al>politiebrevet</al>
                           </li>
                           <li>
                              <li.nr>&#x2013;</li.nr>
                              <al>rangonderscheidingstekens</al>
                           </li>
                           <li>
                              <li.nr>&#x2013;</li.nr>
                              <al>regenbroek</al>
                           </li>
                           <li>
                              <li.nr>&#x2013;</li.nr>
                              <al>schoenen</al>
                           </li>
                           <li>
                              <li.nr>&#x2013;</li.nr>
                              <al>slip-over</al>
                           </li>
                           <li>
                              <li.nr>&#x2013;</li.nr>
                              <al>sokken</al>
                           </li>
                           <li>
                              <li.nr>&#x2013;</li.nr>
                              <al>stropdas/lavalli&#xE8;re</al>
                           </li>
                           <li>
                              <li.nr>&#x2013;</li.nr>
                              <al>trui</al>
                           </li>
                           <li>
                              <li.nr>&#x2013;</li.nr>
                              <al>vangsnoer/armkoord</al>
                           </li>
                           <li>
                              <li.nr>&#x2013;</li.nr>
                              <al>witte
handschoenen</al>
                           </li>
                           <li>
                              <li.nr>&#x2013;</li.nr>
                              <al>zichtbaarheidvest</al>
                           </li>
                        </lijst></divisie><divisie opmaak="default"><kop>
                           <titel status="officieel">Bijzondere
pakketten</titel>
                        </kop><lijst level="single" nr-sluiting="." start="1" type="expliciet">
                           <li>
                              <li.nr>a.</li.nr>
                              <al>Uniform
motorrijders
(heren/dames)</al>
                              <lijst level="single" nr-sluiting="." start="1" type="expliciet">
                                 <li>
                                    <li.nr>&#x2013;</li.nr>
                                    <al>col</al>
                                 </li>
                                 <li>
                                    <li.nr>&#x2013;</li.nr>
                                    <al>halsdoek</al>
                                 </li>
                                 <li>
                                    <li.nr>&#x2013;</li.nr>
                                    <al>helm</al>
                                 </li>
                                 <li>
                                    <li.nr>&#x2013;</li.nr>
                                    <al>motorhandschoenen</al>
                                 </li>
                                 <li>
                                    <li.nr>&#x2013;</li.nr>
                                    <al>motorlaarzen</al>
                                 </li>
                                 <li>
                                    <li.nr>&#x2013;</li.nr>
                                    <al>motorpak,
zomer- en winter
uitvoering</al>
                                 </li>
                                 <li>
                                    <li.nr>&#x2013;</li.nr>
                                    <al>onderkleding</al>
                                 </li>
                                 <li>
                                    <li.nr>&#x2013;</li.nr>
                                    <al>poloshirt
korte mouw</al>
                                 </li>
                                 <li>
                                    <li.nr>&#x2013;</li.nr>
                                    <al>poloshirt lange
mouw</al>
                                 </li>
                                 <li>
                                    <li.nr>&#x2013;</li.nr>
                                    <al>regenkleding</al>
                                 </li>
                                 <li>
                                    <li.nr>&#x2013;</li.nr>
                                    <al>tochtkraag</al>
                                 </li>
                                 <li>
                                    <li.nr>&#x2013;</li.nr>
                                    <al>windstopper</al>
                                 </li>
                                 <li>
                                    <li.nr>&#x2013;</li.nr>
                                    <al>zonnebril</al>
                                 </li>
                              </lijst>
                           </li>
                           <li>
                              <li.nr>b.</li.nr>
                              <al>Uniform
beredenen
(heren/dames)</al>
                              <lijst level="single" nr-sluiting="." start="1" type="expliciet">
                                 <li>
                                    <li.nr>&#x2013;</li.nr>
                                    <al>blouson</al>
                                 </li>
                                 <li>
                                    <li.nr>&#x2013;</li.nr>
                                    <al>col</al>
                                 </li>
                                 <li>
                                    <li.nr>&#x2013;</li.nr>
                                    <al>handschoenen</al>
                                 </li>
                                 <li>
                                    <li.nr>&#x2013;</li.nr>
                                    <al>helm</al>
                                 </li>
                                 <li>
                                    <li.nr>&#x2013;</li.nr>
                                    <al>onderkleding</al>
                                 </li>
                                 <li>
                                    <li.nr>&#x2013;</li.nr>
                                    <al>parka</al>
                                 </li>
                                 <li>
                                    <li.nr>&#x2013;</li.nr>
                                    <al>poloshirt
korte mouw</al>
                                 </li>
                                 <li>
                                    <li.nr>&#x2013;</li.nr>
                                    <al>poloshirt lange
mouw</al>
                                 </li>
                                 <li>
                                    <li.nr>&#x2013;</li.nr>
                                    <al>regenbroek</al>
                                 </li>
                                 <li>
                                    <li.nr>&#x2013;</li.nr>
                                    <al>regencape</al>
                                 </li>
                                 <li>
                                    <li.nr>&#x2013;</li.nr>
                                    <al>rijbroek</al>
                                 </li>
                                 <li>
                                    <li.nr>&#x2013;</li.nr>
                                    <al>rijlaarzen</al>
                                    <al>
                                       <nadruk type="vet">Voor
oefenwerkzaamheden;</nadruk>
                                    </al>
                                 </li>
                                 <li>
                                    <li.nr>&#x2013;</li.nr>
                                    <al>helm</al>
                                 </li>
                                 <li>
                                    <li.nr>&#x2013;</li.nr>
                                    <al>poloshirt
korte mouw</al>
                                 </li>
                                 <li>
                                    <li.nr>&#x2013;</li.nr>
                                    <al>poloshirt lange
mouw</al>
                                 </li>
                              </lijst>
                           </li>
                           <li>
                              <li.nr>c.</li.nr>
                              <al>Uniform
hondengeleiders
(heren/dames)</al>
                              <lijst level="single" nr-sluiting="." start="1" type="expliciet">
                                 <li>
                                    <li.nr>&#x2013;</li.nr>
                                    <al>cap</al>
                                 </li>
                                 <li>
                                    <li.nr>&#x2013;</li.nr>
                                    <al>poloshirt
korte mouw</al>
                                 </li>
                                 <li>
                                    <li.nr>&#x2013;</li.nr>
                                    <al>poloshirt lange
mouw</al>
                                 </li>
                                 <li>
                                    <li.nr>&#x2013;</li.nr>
                                    <al>schoenen</al>
                                 </li>
                                 <li>
                                    <li.nr>&#x2013;</li.nr>
                                    <al>werkbroek</al>
                                    <al>
                                       <nadruk type="vet">Voor
oefenwerkzaamheden;</nadruk>
                                    </al>
                                 </li>
                                 <li>
                                    <li.nr>&#x2013;</li.nr>
                                    <al>werkpak</al>
                                 </li>
                              </lijst>
                           </li>
                           <li>
                              <li.nr>d.</li.nr>
                              <al>Uniform bikers
(heren/dames)</al>
                              <lijst level="single" nr-sluiting="." start="1" type="expliciet">
                                 <li>
                                    <li.nr>&#x2013;</li.nr>
                                    <al>blouson</al>
                                 </li>
                                 <li>
                                    <li.nr>&#x2013;</li.nr>
                                    <al>handschoenen</al>
                                 </li>
                                 <li>
                                    <li.nr>&#x2013;</li.nr>
                                    <al>helm</al>
                                 </li>
                                 <li>
                                    <li.nr>&#x2013;</li.nr>
                                    <al>helmmuts</al>
                                 </li>
                                 <li>
                                    <li.nr>&#x2013;</li.nr>
                                    <al>korte
broek</al>
                                 </li>
                                 <li>
                                    <li.nr>&#x2013;</li.nr>
                                    <al>lange
broek</al>
                                 </li>
                                 <li>
                                    <li.nr>&#x2013;</li.nr>
                                    <al>onderkleding</al>
                                 </li>
                                 <li>
                                    <li.nr>&#x2013;</li.nr>
                                    <al>onderjack/windstopper</al>
                                 </li>
                                 <li>
                                    <li.nr>&#x2013;</li.nr>
                                    <al>poloshirt</al>
                                 </li>
                                 <li>
                                    <li.nr>&#x2013;</li.nr>
                                    <al>poloshirt</al>
                                 </li>
                                 <li>
                                    <li.nr>&#x2013;</li.nr>
                                    <al>schoenen</al>
                                 </li>
                                 <li>
                                    <li.nr>&#x2013;</li.nr>
                                    <al>sokken</al>
                                 </li>
                                 <li>
                                    <li.nr>&#x2013;</li.nr>
                                    <al>zonnebril</al>
                                 </li>
                              </lijst>
                           </li>
                           <li>
                              <li.nr>e.</li.nr>
                              <al>uniform waterpolitie/uniform strand- en
recreatiepolitie
(heren/dames)</al>
                              <al>
                                 <nadruk type="vet">waterpolitie</nadruk>
                              </al>
                              <lijst level="single" nr-sluiting="." start="1" type="expliciet">
                                 <li>
                                    <li.nr>&#x2013;</li.nr>
                                    <al>blouson</al>
                                 </li>
                                 <li>
                                    <li.nr>&#x2013;</li.nr>
                                    <al>col</al>
                                 </li>
                                 <li>
                                    <li.nr>&#x2013;</li.nr>
                                    <al>parka</al>
                                 </li>
                                 <li>
                                    <li.nr>&#x2013;</li.nr>
                                    <al>veiligheidsschoenen</al>
                                 </li>
                              </lijst>
                              <al>
                                 <nadruk type="vet">voor
strand- en
recreatiepolitie</nadruk>
                              </al>
                              <lijst level="single" nr-sluiting="." start="1" type="expliciet">
                                 <li>
                                    <li.nr>&#x2013;</li.nr>
                                    <al>korte
broek</al>
                                 </li>
                                 <li>
                                    <li.nr>&#x2013;</li.nr>
                                    <al>poloshirt</al>
                                 </li>
                                 <li>
                                    <li.nr>&#x2013;</li.nr>
                                    <al>schoenen</al>
                                 </li>
                                 <li>
                                    <li.nr>&#x2013;</li.nr>
                                    <al>sokken</al>
                                 </li>
                              </lijst>
                           </li>
                           <li>
                              <li.nr>f.</li.nr>
                              <al>uniform Mobiele Eenheden
(heren/dames)</al>
                              <lijst level="single" nr-sluiting="." start="1" type="expliciet">
                                 <li>
                                    <li.nr>&#x2013;</li.nr>
                                    <al>cap</al>
                                 </li>
                                 <li>
                                    <li.nr>&#x2013;</li.nr>
                                    <al>helm</al>
                                 </li>
                                 <li>
                                    <li.nr>&#x2013;</li.nr>
                                    <al>ME-bovenkleding</al>
                                 </li>
                                 <li>
                                    <li.nr>&#x2013;</li.nr>
                                    <al>ME-handschoenen</al>
                                 </li>
                                 <li>
                                    <li.nr>&#x2013;</li.nr>
                                    <al>ME-onderkleding</al>
                                 </li>
                                 <li>
                                    <li.nr>&#x2013;</li.nr>
                                    <al>ME-schoenen</al>
                                 </li>
                                 <li>
                                    <li.nr>&#x2013;</li.nr>
                                    <al>poloshirt
korte mouw</al>
                                 </li>
                                 <li>
                                    <li.nr>&#x2013;</li.nr>
                                    <al>poloshirt lange
mouw</al>
                                 </li>
                                 <li>
                                    <li.nr>&#x2013;</li.nr>
                                    <al>protectiemiddelen</al>
                                 </li>
                                 <li>
                                    <li.nr>&#x2013;</li.nr>
                                    <al>sokken</al>
                                 </li>
                              </lijst>
                           </li>
                           <li>
                              <li.nr>g.</li.nr>
                              <al>uniform Verkeerspolitie
(heren/dames)</al>
                              <lijst level="single" nr-sluiting="." start="1" type="expliciet">
                                 <li>
                                    <li.nr>&#x2013;</li.nr>
                                    <al>blouson</al>
                                 </li>
                                 <li>
                                    <li.nr>&#x2013;</li.nr>
                                    <al>overbroek</al>
                                 </li>
                                 <li>
                                    <li.nr>&#x2013;</li.nr>
                                    <al>parka</al>
                                 </li>
                              </lijst>
                           </li>
                           <li>
                              <li.nr>h.</li.nr>
                              <al>Uniform t.b.v. operationeel ondersteunende
medewerkers met publiekscontacten
(heren/dames)</al>
                              <lijst level="single" nr-sluiting="." start="1" type="expliciet">
                                 <li>
                                    <li.nr>&#x2013;</li.nr>
                                    <al>blouson</al>
                                 </li>
                                 <li>
                                    <li.nr>&#x2013;</li.nr>
                                    <al>col</al>
                                 </li>
                                 <li>
                                    <li.nr>&#x2013;</li.nr>
                                    <al>colbert</al>
                                 </li>
                                 <li>
                                    <li.nr>&#x2013;</li.nr>
                                    <al>handschoenen</al>
                                 </li>
                                 <li>
                                    <li.nr>&#x2013;</li.nr>
                                    <al>koppel/riem</al>
                                 </li>
                                 <li>
                                    <li.nr>&#x2013;</li.nr>
                                    <al>overhemd/blouse</al>
                                 </li>
                                 <li>
                                    <li.nr>&#x2013;</li.nr>
                                    <al>onderkleding</al>
                                 </li>
                                 <li>
                                    <li.nr>&#x2013;</li.nr>
                                    <al>pantalon</al>
                                 </li>
                                 <li>
                                    <li.nr>&#x2013;</li.nr>
                                    <al>parka</al>
                                 </li>
                                 <li>
                                    <li.nr>&#x2013;</li.nr>
                                    <al>poloshirt
korte mouw</al>
                                 </li>
                                 <li>
                                    <li.nr>&#x2013;</li.nr>
                                    <al>poloshirt lange
mouw</al>
                                 </li>
                                 <li>
                                    <li.nr>&#x2013;</li.nr>
                                    <al>regenkleding</al>
                                 </li>
                                 <li>
                                    <li.nr>&#x2013;</li.nr>
                                    <al>schoenen</al>
                                 </li>
                                 <li>
                                    <li.nr>&#x2013;</li.nr>
                                    <al>slip-over</al>
                                 </li>
                                 <li>
                                    <li.nr>&#x2013;</li.nr>
                                    <al>sokken</al>
                                 </li>
                                 <li>
                                    <li.nr>&#x2013;</li.nr>
                                    <al>sportkleding</al>
                                 </li>
                                 <li>
                                    <li.nr>&#x2013;</li.nr>
                                    <al>sportschoenen</al>
                                 </li>
                                 <li>
                                    <li.nr>&#x2013;</li.nr>
                                    <al>stropdas</al>
                                 </li>
                                 <li>
                                    <li.nr>&#x2013;</li.nr>
                                    <al>trui</al>
                                 </li>
                                 <li>
                                    <li.nr>&#x2013;</li.nr>
                                    <al>veiligheidsschoenen</al>
                                 </li>
                                 <li>
                                    <li.nr>&#x2013;</li.nr>
                                    <al>werkbroek</al>
                                 </li>
                                 <li>
                                    <li.nr>&#x2013;</li.nr>
                                    <al>werkhandschoenen</al>
                                 </li>
                                 <li>
                                    <li.nr>&#x2013;</li.nr>
                                    <al>werkjas</al>
                                 </li>
                              </lijst>
                           </li>
                        </lijst></divisie></divisie>        </bijlage>    <bijlage status="goed"> 
  <kop> 
	 <label>Bijlage</label> 
	 <nr status="officieel">2</nr> 
	 <titel status="officieel">behorende bij <intref status="actief" doc="1.0:v:BWBR0006553&amp;artikel=1">artikel 1, onderdeel a</intref>, van de Kledingregeling voor de
politie
</titel> 
  <subtitel>Uitmonstering</subtitel></kop> 
  <artikel status="goed"> 
	 <kop> 
		<titel status="officieel">Het
Politiebrevet</titel> 
	 </kop> 
	 <lid> 
		<lidnr status="officieel">1</lidnr> 
		<al>Het
politiebrevet bestaat uit de afbeelding, zoals deze is opgenomen in
hoofdstuk 7 van het handboek politielogo en huisstijl, dat ter inzage
ligt bij het Ministerie van Veiligheid en
Justitie.</al> 
	 </lid> 
	 <lid> 
		<lidnr status="officieel">2</lidnr> 
		<al>Het politiebrevet wordt
gedragen door de uniformdragende ambtenaar, zijnde een ambtenaar als
bedoeld in <extref status="actief" doc="1.0:v:BWBR0006981&amp;artikel=2" compleet="nee">artikel 2, eerste lid</extref>, of <extref status="actief" doc="1.0:v:BWBR0006981&amp;artikel=2a" compleet="nee">artikel 2a, tweede lid, van het
Besluit rangen politie</extref>, en be&#xEB;digd als bedoeld in <extref status="actief" doc="1.0:v:BWBR0006516&amp;artikel=9" compleet="nee">artikel 9 van
het Besluit algemene Rechtspositie Politie</extref>, alsmede door de
uniformdragende ambtenaar, belast met operationele taken met
publiekscontacten, niet zijnde een ambtenaar als bedoeld in artikel 2,
eerste lid, of artikel 2a, tweede lid, van het Besluit rangen politie,
maar wel be&#xEB;digd als bedoeld in artikel 9 van het Besluit algemene
Rechtspositie Politie, op het colbert, de parka en de blouson en wel op
de rechterborst, in de daarvoor in het betreffende kledingstuk
aangebrachte bevestigingsopeningen. Op overige kledingstukken wordt
geen politiebrevet gedragen.</al> 
	 </lid> 
	  
  </artikel> 
  <artikel status="goed"> 
	 <kop> 
		<titel status="officieel">Het politie-logo en het politie-beeldmerk</titel> 
	 </kop> 
	 <lid> 
		<lidnr status="officieel">1</lidnr> 
		<al>Het politie-logo bestaat uit de afbeelding, zoals opgenomen in
		  hoofdstuk 7 van het handboek politielogo en huisstijl.</al> 
	 </lid> 
	 <lid> 
		<lidnr status="officieel">2</lidnr> 
		<al>Het politie-beeldmerk uit het politielogo bestaat uit de afbeelding,
		  zoals opgenomen in hoofdstuk 7 van het handboek politielogo en huisstijl.</al> 
	 </lid> 
	 <lid> 
		<lidnr status="officieel">3</lidnr> 
		<al>Het politie-logo en het -beeldmerk worden op de uniformkleding
		  gedragen overeenkomstig de in hoofdstuk 7 van het handboek politielogo en
		  huisstijl neergelegde aanwijzingen.</al> 
	 </lid> 
  </artikel> 
  <artikel status="goed"> 
	 <kop> 
		<titel status="officieel">De onderscheidingstekens</titel> 
	 </kop> 
	 <lid> 
		<lidnr status="officieel">1</lidnr> 
		<lijst level="single" nr-sluiting="" start="1" type="expliciet"> 
		  <li> 
			 <li.nr>a.</li.nr> 
			 <al>hoofdcommissaris en hoofdcommissaris titulair </al> 
			 <al>Op de schouderbedekkingen:</al> 
			 <al>Een horizontale lauwertak, twee gekruiste zwaarden en een
				rijkskroon, in goud uitgevoerd.</al> 
			 <al>Op de petklep:</al> 
			 <al>Een gouden borduursel van eikebladeren, breed 13 mm, bezet met 6
				eikels, aangebracht op een afstand van 5 mm van het omboordsel. Dit borduursel
				is eveneens aangebracht langs de bovenrand, waar de klep aan de opstaande rand
				van de pet is bevestigd.</al> 
		  </li> 
		  <li> 
			 <li.nr>b.</li.nr> 
			 <al>commissaris: </al> 
			 <al>Op de schouderbedekkingen:</al> 
			 <al>Een horizontale lauwertak met rijkskroon, in goud
				uitgevoerd.</al> 
			 <al>Op de petklep:</al> 
			 <al>Een gouden borduursel van eikebladeren, breed 13 mm, bezet met 6
				eikels, aangebracht op een afstand van 5 mm van het omboordsel.</al> 
		  </li> 
		  <li> 
			 <li.nr>c.</li.nr> 
			 <al>hoofdinspecteur: </al> 
			 <al>Op de schouderbedekkingen:</al> 
			 <al>Een galon met rijkskroon, in goud uitgevoerd.</al> 
			 <al>Op de petklep:</al> 
			 <al>Een gouden borduursel van eikebladeren, aangebracht op een
				afstand van 5 mm van het omboordsel.</al> 
		  </li> 
		  <li> 
			 <li.nr>d.</li.nr> 
			 <al>inspecteur: </al> 
			 <al>Op de schouderbedekkingen:</al> 
			 <al>Een rijkskroon, in goud uitgevoerd.</al> 
			 <al>Op de petklep:</al> 
			 <al>Een gouden galon, breed 10 mm, aangebracht op een afstand van 5
				mm van het omboordsel.</al> 
		  </li> 
		  <li> 
			 <li.nr>e.</li.nr> 
			 <al>brigadier: </al> 
			 <al>Op de schouderbedekkingen:</al> 
			 <al>Twee gebogen lauwertakken, waarin een kleine rijkskroon met
				zwaard is geplaatst, in goud uitgevoerd.</al> 
		  </li> 
		  <li> 
			 <li.nr>f.</li.nr> 
			 <al>hoofdagent: </al> 
			 <al>Op de schouderbedekkingen:</al> 
			 <al>Vier goudkleurige galons.</al> 
		  </li> 
		  <li> 
			 <li.nr>g.</li.nr> 
			 <al>agent: </al> 
			 <al>Op de schouderbedekkingen:</al> 
			 <al>Drie goudkleurige galons.</al> 
		  </li> 
		  <li> 
			 <li.nr>h.</li.nr> 
			 <al>surveillant van politie: </al> 
			 <al>Op de schouderbedekkingen:</al> 
			 <al>Twee goudkleurige galons.</al> 
		  </li> 
		  <li> 
			 <li.nr>i.</li.nr> 
			 <al>adspirant: </al> 
			 <al>Op de schouderbedekkingen:</al> 
			 <al>E&#xE9;n goudkleurige galon.</al> 
		  </li> 
		</lijst> 
	 </lid> 
	 <lid> 
		<lidnr status="officieel">2</lidnr> 
		<al>De onderscheidingstekens voldoen aan de modellen en technische
		  voorschriften, zoals opgenomen in hoofdstuk 7 van het handboek politielogo en
		  huisstijl.</al> 
	 </lid> 
  <lid><lidnr status="officieel">3</lidnr><al>De
schouderbedekkingen voor de uniformdragende ambtenaar, belast met
operationele taken met publiekscontacten, niet zijnde een ambtenaar als
bedoeld in <extref status="actief" doc="1.0:v:BWBR0006981&amp;artikel=2" compleet="nee">artikel 2, eerste lid</extref>, of <extref status="actief" doc="1.0:v:BWBR0006981&amp;artikel=2a" compleet="nee">artikel 2a, tweede lid, van het
Besluit rangen politie</extref>, maar wel be&#xEB;digd als bedoeld in <extref status="actief" doc="1.0:v:BWBR0006516&amp;artikel=9" compleet="nee">artikel 9
van het Besluit algemene Rechtspositie Politie</extref>, bestaan
uit:</al><lijst level="single" nr-sluiting="." start="1" type="expliciet">
                              <li>
                                 <li.nr>&#x2013;</li.nr>
                                 <al>op
het overhemd een epaulet, nassaublauw, voorzien van een geborduurd,
goudkleurig logo:</al>
                              </li>
                              <li>
                                 <li.nr>&#x2013;</li.nr>
                                 <al>op het
colbert een metalen goudkleurig logo (formaat kraag-logo
overjas);</al>
                              </li>
                              <li>
                                 <li.nr>&#x2013;</li.nr>
                                 <al>op de parka/blouson
een blauwzwarte schuifpassant voorzien van een geborduurd, goudkleurig
logo.</al>
                              </li>
                           </lijst></lid></artikel> 
  <artikel status="goed"> 
	 <kop> 
		<titel status="officieel">Het vangsnoer</titel> 
	 </kop> 
	 <al>Het vangsnoer (voor de heren) en het armsnoer (voor de dames), zoals
		afgebeeld in hoofdstuk 7 van het handboek politielogo en huisstijl, wordt op
		aanwijzing van de korpsbeheerder op het
colbert gedragen aan de linker schouder, c.q. de linker arm bij offici&#xEB;le of
		feestelijke gelegenheden.</al> 
  </artikel> 
  <artikel status="goed"> 
	 <kop> 
		<titel status="officieel">Dienstonderscheidingstekens</titel> 
	 </kop> 
	 <lid> 
		<lidnr status="officieel">1</lidnr> 
		<al>Varend politiepersoneel </al> 
		<al>De uitmonstering van varend personeel is gelijk aan de onder A tot en
		  met D beschreven uitmonstering.</al> 
		<al>Door degenen die deel uitmaken van een onderdeel dat meer specifiek
		  is belast met de uitoefening van de politietaak te water  en die hebben voldaan aan de
hiertoe door hun Dienst- of Unithoofd vastgestelde
opleidingseisen, wordt daarnaast het
		  volgende dienstonderscheidingsteken gedragen: een goudkleurig onklaar anker,
		  zoals afgebeeld in hoofdstuk 7 van het handboek politielogo en huisstijl.</al> 
	 </lid> 
	 <lid> 
		<lidnr status="officieel">2</lidnr> 
		<al>Vliegend politiepersoneel </al> 
		<al>De uitmonstering van het vliegend personeel is gelijk aan de onder A
		  tot en met D beschreven uitmonstering.</al> 
		<al>Door degenen die deel uitmaken van een onderdeel dat meer specifiek
		  is belast met de uitoefening van de politietaak door middel van de luchtvaart
		  en die bevoegd zijn tot het besturen van politie-luchtvaartuigen wordt
		  daarnaast het volgende dienstonderscheidingsteken gedragen: een goudkleurige
		  metalen wing met in het midden het beeldmerk uit het politielogo, zoals
		  afgebeeld in hoofdstuk 7 van het handboek politielogo en huisstijl.</al> 
	 </lid> 
	 <lid> 
		<lidnr status="officieel">3</lidnr> 
		<al>De
dienstonderscheidingstekens worden gedragen op het colbert, de parka en
de blouson, en wel op de linkerborst ter hoogte van de
oksel.</al> 
	 </lid> 
	 <lid> 
		<lidnr status="officieel">4</lidnr> 
		<al>De dienstonderscheidingstekens voldoen aan de modellen en technische
		  voorschriften, zoals opgenomen in hoofdstuk 7 van het handboek politielogo en
		  huisstijl.</al> 
	 </lid> 
  </artikel> 
</bijlage>    </regeling>  </wetgeving>
  	