<?xml version="1.0"?>
<!DOCTYPE wetgeving SYSTEM "http://wetten.overheid.nl/dtd/bwb-plus-meta-1_61w.dtd">
<wetgeving bwb-id="BWBV0002939" dtdversie="2.0" id="10000024139" verdragnummer="000226" soort="verdrag"><intitule>Overeenkomst tussen het Koninkrijk der Nederlanden en de Arabische Republiek Egypte inzake het Nederlands Instituut voor Archeologie en Arabische Studien te Kairo</intitule><verdrag tekst="authentiek" xml:lang="en">
    <verdragtekst>
      <kop>
        <titel status="officieel">Agreement between the Kingdom of the Netherlands and the Arab Republic of Egypt concerning the Netherlands Institute of Archaeology and Arabic Studies at Cairo</titel>
      </kop>
      <aanhef>
        <preambule>
          <al>The Kingdom of the Netherlands and the Arab Republic of Egypt;</al>
          <al>Desiring to further strengthen the cooperation between their respective countries provided for under the Cultural Agreement which was concluded by both parties in The Hague on 8 December 1960;</al>
          <al>Have agreed as follows:</al>
        </preambule>
      </aanhef>
      <wettekst>
        <artikel status="goed">
          <kop>
            <label>Article</label>
            <nr status="officieel">1</nr>
          </kop>
          <al>The Netherlands Institute of Archaeology and Arabic Studies, hereinafter referred to as "the Institute", shall be an institution that has legal personality under Egyptian law and is established in Cairo by the University of Leiden.</al>
        </artikel>
        <artikel status="goed">
          <kop>
            <label>Article</label>
            <nr status="officieel">2</nr>
          </kop>
          <al>The object of the Institute shall be to promote Egyptology, archaeology, papyrology and Hellenistic and Coptic studies as well as Arabic studies in the broadest sense.</al>
        </artikel>
        <artikel status="goed">
          <kop>
            <label>Article</label>
            <nr status="officieel">3</nr>
          </kop>
          <al>In order to achieve this aim the Institute:</al>
          <lijst level="single" nr-sluiting="." start="1" type="expliciet">
            <li>
              <li.nr>a)</li.nr>
              <al>shall regularly issue publications on subjects related to the scientific studies referred to in Article 2;</al>
            </li>
            <li>
              <li.nr>b)</li.nr>
              <al>shall administer a library for the study of these scientific topics;</al>
            </li>
            <li>
              <li.nr>c)</li.nr>
              <al>shall offer hospitality and where possible provide assistance to Netherlands citizens who are staying in the Arab Republic of Egypt for the purposes of study or research, or both, and may similarly offer hospitality and where possible provide assistance to persons other than those of Netherlands nationality who are staying in the Arab Republic of Egypt for the purposes of conducting scientific research on behalf of or in cooperation with Netherlands institutes for scientific research;</al>
            </li>
            <li>
              <li.nr>d)</li.nr>
              <al>shall cooperate with Netherlands archaeological expeditions, the Institute's building acting as base;</al>
            </li>
            <li>
              <li.nr>e)</li.nr>
              <al>shall in general make its facilities available for the purposes of disseminating information on Netherlands science and culture.</al>
            </li>
          </lijst>
        </artikel>
        <artikel status="goed">
          <kop>
            <label>Article</label>
            <nr status="officieel">4</nr>
          </kop>
          <al>The general management of the Institute and the management of research conducted in it shall be the responsibility of a Board of Governors consisting of not more than nine members. The following persons shall be members of the Board:</al>
          <lijst level="single" nr-sluiting="." start="1" type="expliciet">
            <li>
              <li.nr>a)</li.nr>
              <al>a professor of Arabic from the University of Leiden;</al>
            </li>
            <li>
              <li.nr>b)</li.nr>
              <al>another professor from the University of Leiden;</al>
            </li>
            <li>
              <li.nr>c)</li.nr>
              <al>a representative of the National Museum of Antiquities in Leiden;</al>
            </li>
            <li>
              <li.nr>d)</li.nr>
              <al>members of the research staff of Netherlands universities.</al>
            </li>
          </lijst>
        </artikel>
        <artikel status="goed">
          <kop>
            <label>Article</label>
            <nr status="officieel">5</nr>
          </kop>
          <al>The day-to-day management of the Institute shall be the responsibility of the Director of the Institute.</al>
        </artikel>
        <artikel status="goed">
          <kop>
            <label>Article</label>
            <nr status="officieel">6</nr>
          </kop>
          <al>The Government of the Arab Republic of Egypt shall grant the Director and the Netherlands staff of the Institute as well as members of their families all facilities related to their entry into and stay in Egyptian territory, in accordance with the legislation of the Arab Republic of Egypt, notably with respect to the provision of residence and work permits free of charge to the above-mentioned persons of Netherlands nationality.</al>
        </artikel>
        <artikel status="goed">
          <kop>
            <label>Article</label>
            <nr status="officieel">7</nr>
          </kop>
          <al>The Government of the Arab Republic of Egypt shall exempt the Director and the Netherlands staff of the Institute and the members of their families from customs duties and other import taxes or duties on new or used household effects and personal belongings imported into Egypt within six months of their arrival, provided that such goods are re-exported from Egypt at the time of departure or within such period thereafter as may be acceptable to the Government of the Arab Republic of Egypt.</al>
        </artikel>
        <artikel status="goed">
          <kop>
            <label>Article</label>
            <nr status="officieel">8</nr>
          </kop>
          <al>The Government of the Arab Republic of Egypt shall make provision for the duty-free importation or purchase from bond by the Institute of one motor-vehicle, provided that such vehicle, if sold to a person not likewise privileged, shall be subject to customs duties according to Egyptian law.</al>
          <al>The Government of the Arab Republic of Egypt shall make provision for the duty-free importation or purchase from bond by the Director or the Netherlands staff of the Institute of a motor-vehicle within six months of first arrival in Egypt, provided that such vehicle, if sold to a person not likewise privileged, shall be subject to customs duties according to Egyptian law.</al>
        </artikel>
        <artikel status="goed">
          <kop>
            <label>Article</label>
            <nr status="officieel">9</nr>
          </kop>
          <al>The Institute shall enjoy the following fiscal privileges, which do not include the amounts payable for services rendered:</al>
          <lijst level="single" nr-sluiting="." start="1" type="expliciet">
            <li>
              <li.nr>a)</li.nr>
              <al>exception from all taxes, charges and payments for acquisition, whether or not there is any valuable consideration, and use of land and buildings intended to serve as the seat of the Institute;</al>
            </li>
            <li>
              <li.nr>b)</li.nr>
              <al>exemption from import duties and all other charges on the import of furniture, teaching and research material, and books and publications needed for the setting up and functioning of the institute.</al>
            </li>
          </lijst>
        </artikel>
        <artikel status="goed">
          <kop>
            <label>Article</label>
            <nr status="officieel">10</nr>
          </kop>
          <al>The Egyptian authorities shall provide all administrative facilities required for the distribution outside Egypt of publications produced under the responsibility of the Institute.</al>
        </artikel>
        <artikel status="goed">
          <kop>
            <label>Article</label>
            <nr status="officieel">11</nr>
          </kop>
          <al>This Agreement shall enter into force on the first day of the second month after the date on which both Governments have informed each other in writing that the procedures constitutionally required therefore in their respective countries have been complied with.</al>
        </artikel>
        <artikel status="goed">
          <kop>
            <label>Article</label>
            <nr status="officieel">12</nr>
          </kop>
          <al>With respect to the Kingdom of the Netherlands, this Agreement shall apply solely to the part of the Kingdom in Europe.</al>
        </artikel>
        <artikel status="goed">
          <kop>
            <label>Article</label>
            <nr status="officieel">13</nr>
          </kop>
          <al>This Agreement shall remain in force for an initial period of three years. If it has not been denounced three months before the date of its termination, it shall be tacitly renewed for periods of two years at a time.</al>
          <al>Each Government shall then have the right to denounce the Agreement at any time by giving three months' notice to the other Government.</al>
        </artikel>
      </wettekst>
      <wetsluiting status="goed">
        <slotformulering>
          <al>IN WITNESS WHEREOF the undersigned, being duly authorized thereto by their respective Governments, have signed this Agreement.</al>
          <al>DONE in duplicate in the English language at Cairo on May 25, 1983.</al>
          <al>
            <nadruk type="cur">For the Kingdom of the Netherlands:</nadruk></al>
          
          <al>Mr. P. Buwalda</al>
          <al>Ambassador Extraordinary and Plenipotentiary of Her Majesty the Queen of the Netherlands at Cairo </al>
          <al>(Sd.) P. BUWALDA</al>
          <al>
            <nadruk type="cur">For the Arab Republic of Egypt:</nadruk></al>
          
          <al>Ambassador Aly Shawky El Hadidy</al>
          <al>Director of the Cultural Relation and Technical Cooperation Department,</al><al>Ministry of Foreign Affairs</al>
          <al>(Sd.) ALY SHAWKY EL HADIDY</al>
        </slotformulering>
      </wetsluiting>
    </verdragtekst>
    <verdragtekst>
      <kop>
        <label>Nr.</label>
        <nr status="officieel">I</nr>
      </kop>
      <vrije-tekst>
        <tekst status="goed">
          <al>No. 2763</al>
          <al>The Royal Netherlands Embassy presents its compliments to the Ministry of Foreign Affairs of the Arab Republic of Egypt and, referring to the agreement concerning the Netherlands Institute of Archaeology and Arabic Studies, which is to be signed once a date will have been set by the Ministry, the Embassy has the honour to inform the Ministry that it is the understanding of the Government of the Kingdom of the Netherlands, that the Government of the Arab Republic of Egypt will not levy any taxes or other fiscal charges in respect of all remunerations paid to the Director and the Netherlands personnel of the Institute out of Netherlands public funds and remitted to them from overseas.</al>
          <al>The Embassy would be grateful to the Ministry if it could confirm that this understanding is correct.</al>
          <al>The Royal Netherlands Embassy avails itself of this opportunity to renew to the Ministry of Foreign Affairs of the Arab Republic of Egypt the assurances of its highest consideration.</al>
          <al>Cairo, April 21, 1983.</al>
          <al>
            <nadruk type="cur">Ministry of Foreign Affairs </nadruk>
          </al>
          <al>
            <nadruk type="cur">International Relations Department </nadruk>
          </al>
          <al>
            <nadruk type="cur">European Section </nadruk>
          </al>
          <al>
            <nadruk type="cur">Cairo</nadruk>
          </al>
          <al>cc: Ministry of Culture</al>
          <al>High Council for International Cultural Relations</al>
          <al>Cairo</al>
        </tekst>
      </vrije-tekst>
    </verdragtekst>
    <verdragtekst>
      <kop>
        <label>Nr.</label>
        <nr status="officieel">II</nr>
      </kop>
      <vrije-tekst>
        <tekst status="goed">
          <al>The Ministry of Foreign Affairs of the Arab Republic of Egypt presents its compliments to the Royal Netherlands Embassy in Cairo, and have the honour to acknowledge receipt of its Note No. 2763 of 21st of April, 1983 referring to the Agreement concerning the Netherlands Institute of Archaeology and Arabic Studies to be signed once a date has been set:</al>
          <al>This Note states the following:</al>
          <al>
            <redactie type="extra">(Zoals in Nr. I)</redactie>
          </al>
          <al>In reply the Ministry informs the Embassy that the above mentioned understanding is correct and acceptable to the Government of the Arab Republic of Egypt and that the Embassy's Note and this reply shall constitute an integral part of the Agreement between the two countries to enter into force as from the date of signature of the Agreement.</al>
          <al>The Ministry of Foreign Affairs, Department of Cultural and Technical Cooperation, avails itself of this opportunity to renew to the Royal Netherlands Embassy in Cairo the assurances of its highest consideration.</al>
          <al>Cairo, May 10th, 1983.</al>
          <tussenkop>
            <nadruk type="cur">To the Royal Netherlands Embassy in Cairo.</nadruk>
          </tussenkop>
        </tekst>
      </vrije-tekst>
    </verdragtekst>
  </verdrag>
  <verdrag tekst="vertaling" xml:lang="nl">
    <verdragtekst>
      <kop>
        <titel status="officieel">Overeenkomst tussen het Koninkrijk der Nederlanden en de Arabische Republiek Egypte inzake het Nederlands Instituut voor Archeologie en Arabische studi&#xEB;n te Kairo</titel>
      </kop>
      <aanhef>
        <preambule>
          <al>Het Koninkrijk der Nederlanden en de Arabische Republiek Egypte, verlangend de samenwerking, vastgelegd in de op 8 december 1960 te 's-Gravenhage tussen beide Partijen tot stand gekomen Culturele Overeenkomst, verder te versterken:</al>
          <al>Zijn overeengekomen als volgt:</al>
        </preambule>
      </aanhef>
      <wettekst>
        <artikel status="goed">
          <kop>
            <label>Artikel</label>
            <nr status="officieel">1</nr>
          </kop>
          <al>Het Nederlandse Instituut voor Archeologie en Arabische studi&#xEB;n, hierna te noemen &#x201E;het Instituut&#x201D;, is een instelling met rechtspersoonlijkheid volgens Egyptisch recht, opgericht te Kairo door de Rijksuniversiteit te Leiden.</al>
        </artikel>
        <artikel status="goed">
          <kop>
            <label>Artikel</label>
            <nr status="officieel">2</nr>
          </kop>
          <al>Het Instituut heeft ten doel de bevordering van de egyptologie, de archeologie, de papyrologie, de hellenistiek, en de koptologie alsmede de Arabische studi&#xEB;n in de ruimste zin.</al>
        </artikel>
        <artikel status="goed">
          <kop>
            <label>Artikel</label>
            <nr status="officieel">3</nr>
          </kop>
          <al>Ter verwerkelijking van deze doelstelling verricht het Instituut het volgende:</al>
          <lijst level="single" nr-sluiting="." start="1" type="expliciet">
            <li>
              <li.nr>a.</li.nr>
              <al>het doet regelmatig publicaties betreffende de in artikel 2 vermelde wetenschapsgebieden verschijnen.</al>
            </li>
            <li>
              <li.nr>b.</li.nr>
              <al>het beheert een bibliotheek ten behoeve van de studie dezer wetenschappen.</al>
            </li>
            <li>
              <li.nr>c.</li.nr>
              <al>het biedt gastvrijheid en waar mogelijk assistentie aan Nederlanders, die voor studie en/of wetenschappelijk onderzoek in de Arabische Republiek Egypte verblijven. Eveneens kan het Instituut gastvrijheid en waar mogelijk assistentie bieden aan personen van andere dan de Nederlandse nationaliteit, die voor wetenschappelijk onderzoek, dat wordt verricht in opdracht van of in samenwerking met Nederlandse instellingenvan wetenschappelijk onderzoek, in de Arabische Republiek Egypte verblijven.</al>
            </li>
            <li>
              <li.nr>d.</li.nr>
              <al>het verleent medewerking aan Nederlandse archeologische expedities. Het gebouw van het Instituut kan deze tot basis dienen.</al>
            </li>
            <li>
              <li.nr>e.</li.nr>
              <al>het stelt in het algemeen zijn faciliteiten ten dienste van het bekendmaken van de Nederlandse wetenschap en cultuur.</al>
            </li>
          </lijst>
        </artikel>
        <artikel status="goed">
          <kop>
            <label>Artikel</label>
            <nr status="officieel">4</nr>
          </kop>
          <al>De algemene en wetenschappelijke leiding van het Instituut berust bij een bestuur, dat uit ten hoogste negen leden bestaat. In het bestuur hebben zitting:</al>
          <lijst level="single" nr-sluiting="." start="1" type="expliciet">
            <li>
              <li.nr>a.</li.nr>
              <al>een hoogleraar Arabisch van de Rijksuniversiteit te Leiden</al>
            </li>
            <li>
              <li.nr>b.</li.nr>
              <al>een andere hoogleraar van de Rijksuniversiteit te Leiden.</al>
            </li>
            <li>
              <li.nr>c.</li.nr>
              <al>een vertegenwoordiger van het Rijksmuseum van Oudheden te Leiden</al>
            </li>
            <li>
              <li.nr>d.</li.nr>
              <al>leden van het wetenschappelijk corps van Nederlandse universiteiten.</al>
            </li>
          </lijst>
        </artikel>
        <artikel status="goed">
          <kop>
            <label>Artikel</label>
            <nr status="officieel">5</nr>
          </kop>
          <al>De dagelijkse leiding van het Instituut berust bij de Directeur van het Instituut.</al>
        </artikel>
        <artikel status="goed">
          <kop>
            <label>Artikel</label>
            <nr status="officieel">6</nr>
          </kop>
          <al>De Regering van de Arabische Republiek Egypte verleent aan de Directeur en het Nederlandse personeel van het Instituut en aan hun gezinsleden alle faciliteiten met betrekking tot de binnenkomst en het verblijf op haar grondgebied, overeenkomstig de wetgeving van de Arabische Republiek Egypte, met name wat betreft de kosteloze verschaffing van verblijfs- en werkvergunningen voor genoemde Nederlandse personen.</al>
        </artikel>
        <artikel status="goed">
          <kop>
            <label>Artikel</label>
            <nr status="officieel">7</nr>
          </kop>
          <al>De Regering van de Arabische Republiek Egypte verleent aan de Directeur en het Nederlandse personeel van het Instituut en aan hun gezinsleden vrijstelling van douanerechten en andere belastingen of heffingen met betrekking tot de invoer van nieuwe of gebruikte huishoudelijke artikelen en persoonlijke bezittingen, ingevoerd in Egypte binnen zes maanden na hun aankomst, mits zodanige goederen weer uit Egypte worden uitgevoerd bij vertrek of binnen een termijn die voor de Regering van de Arabische Republiek Egypte aanvaardbaar zal zijn.</al>
        </artikel>
        <artikel status="goed">
          <kop>
            <label>Artikel</label>
            <nr status="officieel">8</nr>
          </kop>
          <al>De Regering van de Arabische Republiek Egypte regelt de invoer, vrij van rechten, of de aankoop uit entrepot, van &#xE9;&#xE9;n motorvoertuig door het Instituut, mits over dit voertuig, indien het wordt verkocht aan iemand die niet dezelfde voorrechten geniet, invoerrechten worden betaald volgens de Egyptische wet.</al>
          <al>De Regering van de Arabische Republiek Egypte regelt de invoer, vrij van rechten, of de aankoop uit entrepot door de Directeur en andere Nederlandse personeelsleden van het Instituut van een motorvoertuig binnen zes maanden na eerste aankomst in Egypte, mits over dit voertuig, indien het wordt verkocht aan iemand die niet dezelfde voorrechten geniet, invoerrechten worden betaald volgens de Egyptische wet.</al>
        </artikel>
        <artikel status="goed">
          <kop>
            <label>Artikel</label>
            <nr status="officieel">9</nr>
          </kop>
          <al>Het Instituut geniet de volgende voordelen van fiscale aard, welke niet de vergoedingen omvatten die verschuldigd zijn als beloning voor verleende diensten:</al>
          <lijst level="single" nr-sluiting="." start="1" type="expliciet">
            <li>
              <li.nr>a.</li.nr>
              <al>vrijstelling van alle belastingen, heffingen en vergoedingen voor de verwerving, onder bezwarende titel of om niet, en voor het gebruik van gronden en gebouwen bestemd om als zetel van het Instituut te dienen;</al>
            </li>
            <li>
              <li.nr>b.</li.nr>
              <al>vrijstelling van invoerrechten en van alle andere heffingen bij de invoer van meubilair, onderwijsmateriaal en materiaal voor wetenschappelijk onderzoek, van boeken en publicaties nodig voor de inrichting en het functioneren van het Instituut.</al>
            </li>
          </lijst>
        </artikel>
        <artikel status="goed">
          <kop>
            <label>Artikel</label>
            <nr status="officieel">10</nr>
          </kop>
          <al>De Egyptische autoriteiten verlenen alle administratieve faciliteiten voor verspreiding buiten Egypte van publikaties die onder verantwoordelijkheid van het Instituut tot stand komen.</al>
        </artikel>
        <artikel status="goed">
          <kop>
            <label>Artikel</label>
            <nr status="officieel">11</nr>
          </kop>
          <al>Deze Overeenkomst treedt in werking op de eerste dag van de tweede maand, volgend op de datum waarop de beide Regeringen elkaar schriftelijk hebben medegedeeld dat aan de in hun onderscheiden landen constitutioneel vereiste procedures is voldaan.</al>
        </artikel>
        <artikel status="goed">
          <kop>
            <label>Artikel</label>
            <nr status="officieel">12</nr>
          </kop>
          <al>Wat het Koninkrijk der Nederlanden betreft, geldt deze Overeenkomst slechts voor het Rijk in Europa.</al>
        </artikel>
        <artikel status="goed">
          <kop>
            <label>Artikel</label>
            <nr status="officieel">13</nr>
          </kop>
          <al>Deze Overeenkomst blijft van kracht voor een aanvangsperiode van drie jaar. Indien zij niet drie maanden voorafgaand aan de datum van be&#xEB;indiging is opgezegd, wordt zij stilzwijgend verlengd voor achtereenvolgende tijdvakken van twee jaar.</al>
          <al>Elk van beide Regeringen heeft dan het recht de Overeenkomst te allen tijde op te zeggen; zij stelt de andere Regering drie maanden van tevoren hiervan in kennis.</al>
        </artikel>
      </wettekst>
      <wetsluiting status="goed">
        <slotformulering>
          <al>TEN BLIJKE WAARVAN de ondergetekenden, daartoe behoorlijk gemachtigd door hun onderscheiden Regeringen, deze Overeenkomst hebben ondertekend.</al>
          <al>GEDAAN in tweevoud te Kairo op 25 mei 1983, in de Engelse taal.</al>
          <al>
            <nadruk type="cur">Voor het Koninkrijk der Nederlanden:</nadruk></al>
          <al>Mr. P. Buwalda</al>
          <al>Harer Majesteits Buitengewoon en Gevolmachtigd Ambassadeur te Kairo </al>
          <al>(w.g.) P. BUWALDA </al>
          <al>
            <nadruk type="cur">Voor de Arabische Republiek Egypte:</nadruk></al>
          
          <al>El Hadidy</al>
          <al>Directeur van de Afdeling van Culturele Betrekkingen en Technische Samenwerking,</al>
          <al>Ministerie van Buitenlandse Zaken</al>
          <al>(w.g.) ALY SHAWKY EL HADIDY</al>
        </slotformulering>
      </wetsluiting>
    </verdragtekst>
    <verdragtekst>
      <kop>
        <label>Nr.</label>
        <nr status="officieel">I</nr>
      </kop>
      <vrije-tekst>
        <tekst status="goed">
          <al>Nr. 2763</al>
          <al>De Ambassade van het Koninkrijk der Nederlanden biedt het Ministerie van Buitenlandse Zaken van de Arabische Republiek Egypte haar complimenten aan en, onder verwijzing naar de Overeenkomst inzake het Nederlands Instituut voor Archeologie en Arabische Studi&#xEB;n, die zal worden ondertekend zodra daarvoor een datum door het Ministerie zal zijn vastgesteld, heeft de Ambassade de eer het Ministerie mede te delen dat de Regering van het Koninkrijk der Nederlanden ervan uitgaat dat de Regering van de Arabische Republiek Egypte geen belastingen zal heffen of andere fiscale heffingen op zal leggen op alle aan de directeur en het Nederlandse personeel van het Instituut uit Nederlandse overheidsgelden betaalde vergoedingen die aan hen vanuit het buitenland worden overgemaakt.</al>
          <al>De Ambassade zou gaarne van het Ministerie de bevestiging ontvangen van de juistheid van hetgeen hierboven wordt aangenomen.</al>
          <al>De Ambassade van het Koninkrijk der Nederlanden maakt van deze gelegenheid gebruik het Ministerie van Buitenlandse Zaken van de Arabische Republiek Egypte opnieuw de verzekering te geven vanhaar zeer bijzondere hoogachting.</al>
          <al>Kairo, 21 april 1983.</al>
          <al>
            <nadruk type="cur">Ministerie van Buitenlandse Zaken, </nadruk>
          </al>
          <al>
            <nadruk type="cur">Directie Internationale Betrekkingen, </nadruk>
          </al>
          <al>
            <nadruk type="cur">Bureau Europa, </nadruk>
          </al>
          <al>
            <nadruk type="cur">Kairo</nadruk>
          </al>
          <al>cc: Ministerie van Cultuur,</al>
          <al>Hoge Raad voor Internationale Culturele Betrekkingen,</al>
          <al>Kairo</al>
          <tussenkop/>
        </tekst>
      </vrije-tekst>
    </verdragtekst>
    <verdragtekst>
      <kop>
        <label>Nr.</label>
        <nr status="officieel">II</nr>
      </kop>
      <vrije-tekst>
        <tekst status="goed">
          <al>Het Ministerie van Buitenlandse Zaken van de Arabische Republiek Egypte biedt de Ambassade van het Koninkrijk der Nederlanden te Kairo zijn complimenten aan en heeft de eer de ontvangst te bevestigen van haar nota van 21 april 1983, nr. 2763, waarin wordt verwezen naar de Overeenkomst inzake het Nederlands Instituut voor Archeologie en Arabische Studi&#xEB;n, die zal worden ondertekend zodra daarvoor een datum is vastgesteld.</al>
          <al>In deze nota wordt het volgende verklaard:</al>
          <al>
            <redactie type="extra">(Zoals in Nr. I)</redactie>
          </al>
          <al>In antwoord deelt het Ministerie de Ambassade mede dat hetgeen hierboven wordt aangenomen juist is en aanvaardbaar is voor de Regering van de Arabische Republiek Egypte en dat de nota van de Ambassade en dit antwoord een integrerend onderdeel zullen vormen van de Overeenkomst tussen de beide landen, dat in werking zal treden op de datum van ondertekening van de Overeenkomst.</al>
          <al>Het Ministerie van Buitenlandse Zaken, Directie Culturele en Technische Samenwerking, maakt van deze gelegenheid gebruik de Ambassade van het Koninkrijk der Nederlanden te Kairo opnieuw de verzekering te geven van zijn zeer bijzondere hoogachting.</al>
          <al>Kairo, 10 mei 1983.</al>
          <al>
            <nadruk type="cur">Aan de Ambassade van het Koninkrijk der Nederlanden, </nadruk>
          </al>
          <al>
            <nadruk type="cur">Kairo.</nadruk>
          </al>
        </tekst>
      </vrije-tekst>
    </verdragtekst>
  </verdrag></wetgeving>
  	